Workbook

Sheet Index
A1: Organization and Accounting Charts
A2: Beitak Smart - Odoo implementation | Entity data (GAWF). Fictional project data; assumptions on the last rows.
A4: Sheet | B4: Content | C4: Instructor requirement
A5: Company Setup | B5: Company data and basic configuration | C5: Company Foundation / Basic Configuration
A6: Organization Chart | B6: Departments, managers, headcount and users | C6: Entity Data 1 - Organization Chart
A7: Employees | B7: 36 employees with job, department, manager | C7: HR - Departments > Employees
A8: Users per Department | B8: Odoo users and access level per app | C8: Number of users per department / Users Privileges
A9: Chart of Accounts | B9: Final CoA used by the design | C9: Entity Data 2 - CoA
A10: Opening Trial Balance | B10: Opening balances by account, balanced check | C10: Entity Data 3 - Opening Balances
A11: Opening Partner Balances | B11: Opening AR / AP / cheques per partner | C11: Partners chart - Balances
A12: Bank Details | B12: Banks, accounts (placeholders), journals | C12: Entity Data 4 - Bank details
A13: Cash Safes | B13: Safes, custodians, limits and daily cycle | C13: Entity Data 5 - Cash safe details
A14: Journals | B14: Bank, cash and system journals | C14: Entity Data 6 - Chart of Journals
A15: Taxes | B15: VAT and withholding taxes | C15: Entity Data 7 - Tax Chart
... A17: Currencies | B17: EGP and USD with opening rate | C17: Multi-currency
A19: Assumptions
A20: Odoo version | B20: Files target Odoo 18/19 field names (type=Goods + is_storable). On Odoo 17 replace 'type'+'is_storable' with 'detailed_type' = product.
A21: Database | B21: Designed for a NEW clean database with the Egypt fiscal localization. Importing into the old database will clash with existing account codes and products.
A22: Exchange rate | B22: USD/EGP = 50.00 on 2027-01-01. Project assumption, not an official CBE rate.
A23: Landed costs | B23: Cost of imported items = FOB price x 50 x 1.10 (about 10% for freight, duties, clearance and insurance). Assumption.
A24: Sales prices | B24: Sales prices are VAT-exclusive. VAT 14% comes from the Egypt localization default taxes.
A25: Costing | B25: AVCO + automated (perpetual) valuation on all stockable categories. Needed for Landed Costs.
A26: Opening stock | B26: Stock is loaded through Physical Inventory with accounting date 2027-01-01. Its counterpart is account 190100 Opening Stock Clearing, which the opening journal entry closes to zero.
A27: Taxes | B27: VAT 14% and withholding tax 1% / 2% / 3% (team decision). Rates, categories and thresholds must be reviewed by a tax specialist before go-live.
A28: Personal data | B28: All names, emails, phones, tax IDs and bank numbers are fictional placeholders (.example domains).

Sheet Company Setup
A1: Company Setup - Basic Configuration Data
A2: Values entered in Settings > Companies and the app settings.
A4: Setting | B4: Value
A5: Company name | B5: Beitak Smart
A6: Legal form | B6: Joint Stock Company (S.A.E.) - assumption
A7: Activity | B7: Import, distribution and retail of home appliances; in-house assembly of fans and components
A8: Head office | B8: Nasr City, Cairo (placeholder address)
A9: Showroom | B9: Cairo Showroom (POS)
A10: Warehouses | B10: Cairo (Main, CAW), Alexandria (ALW), Mansoura (MAW), Ismailia (ISW), Asyut (ASW)
A11: Company currency | B11: EGP
A12: Foreign currency | B12: USD (opening rate 50.00 EGP - assumption)
A13: Fiscal year | B13: 1 January - 31 December
A14: Fiscal localization | B14: Egypt (chart of accounts, VAT and WHT taxes)
A15: Opening balance date | B15: 2027-01-01
... A21: Employees / Odoo users | B21: 36 employees / 30 users

Sheet Employees
A1: Chart of Employees
A2: Imported with 07_Employees.xlsx. Emails and extensions are placeholders. No salary data is stored.
A4: Emp. No. | B4: Name | C4: Job Position | D4: Job Title | E4: Department | F4: Manager | G4: Work Location | H4: Work Email | I4: Odoo User
A5: EMP-01 | B5: Hany Mostafa | C5: General Manager | D5: General Manager | E5: General Management | F5: - | G5: Cairo HO | H5: hany.mostafa@beitaksmart.example | I5: Yes
A6: EMP-02 | B6: Rania Fathy | C6: Finance Manager | D6: Finance Manager | E6: Finance & Accounting | F6: Hany Mostafa | G6: Cairo HO | H6: rania.fathy@beitaksmart.example | I6: Yes
A7: EMP-03 | B7: Sherif Nabil | C7: Procurement & Import Manager | D7: Procurement & Import Manager | E7: Procurement & Import | F7: Hany Mostafa | G7: Cairo HO | H7: sherif.nabil@beitaksmart.example | I7: Yes
A8: EMP-04 | B8: Karim Adel | C8: Sales Manager | D8: Sales Manager | E8: Sales | F8: Hany Mostafa | G8: Cairo HO | H8: karim.adel@beitaksmart.example | I8: Yes
A9: EMP-05 | B9: Tamer Salah | C9: Warehouse & Logistics Manager | D9: Warehouse & Logistics Manager | E9: Warehouse & Logistics | F9: Hany Mostafa | G9: Cairo Warehouse | H9: tamer.salah@beitaksmart.example | I9: Yes
A10: EMP-06 | B10: Mohamed Zaki | C10: Production Manager | D10: Production Manager | E10: Production | F10: Hany Mostafa | G10: Cairo Warehouse | H10: mohamed.zaki@beitaksmart.example | I10: Yes
A11: EMP-07 | B11: Dina Samir | C11: HR Manager | D11: HR Manager | E11: Human Resources | F11: Hany Mostafa | G11: Cairo HO | H11: dina.samir@beitaksmart.example | I11: Yes
A12: EMP-08 | B12: Omar Hassan | C12: IT & ERP Administrator | D12: IT & ERP Administrator | E12: IT & ERP | F12: Hany Mostafa | G12: Cairo HO | H12: omar.hassan@beitaksmart.example | I12: Yes
A13: EMP-09 | B13: Mahmoud Ali | C13: Senior Accountant | D13: Senior Accountant | E13: Finance & Accounting | F13: Rania Fathy | G13: Cairo HO | H13: mahmoud.ali@beitaksmart.example | I13: Yes
A14: EMP-10 | B14: Nourhan Ibrahim | C14: Accountant | D14: Accountant - AP & AR | E14: Finance & Accounting | F14: Rania Fathy | G14: Cairo HO | H14: nourhan.ibrahim@beitaksmart.example | I14: Yes
A15: EMP-11 | B15: Wael Said | C15: Treasurer / Cashier | D15: Treasurer / Cashier | E15: Finance & Accounting | F15: Rania Fathy | G15: Cairo HO | H15: wael.said@beitaksmart.example | I15: Yes
... A40: EMP-36 | B40: Aya Hesham | C40: HR Specialist | D40: HR Specialist | E40: Human Resources | F40: Dina Samir | G40: Cairo HO | H40: aya.hesham@beitaksmart.example | I40: Yes

Sheet Users per Department
A1: Users & Access Rights per Department
A2: Users are created from the employee form (Create User). Access levels are the Odoo groups to tick on the user form.
A4: User | B4: Job Title | C4: Department | D4: Login | E4: Sales | F4: CRM | G4: Purchase | H4: Inventory | I4: Manufacturing | J4: Accounting | K4: Point of Sale | L4: Employees | M4: Settings
A5: Hany Mostafa | B5: General Manager | C5: General Management | D5: hany.mostafa@beitaksmart.example | E5: Administrator | F5: Administrator | G5: Administrator | H5: Administrator | I5: Administrator | J5: Auditor (read-only) | K5: Administrator | L5: Officer | M5: -
A6: Rania Fathy | B6: Finance Manager | C6: Finance & Accounting | D6: rania.fathy@beitaksmart.example | E6: User: All Documents | F6: - | G6: User | H6: User | I6: - | J6: Administrator | K6: User | L6: - | M6: -
A7: Sherif Nabil | B7: Procurement & Import Manager | C7: Procurement & Import | D7: sherif.nabil@beitaksmart.example | E7: - | F7: - | G7: Administrator | H7: User | I7: - | J7: Invoicing / Billing | K7: - | L7: - | M7: -
A8: Karim Adel | B8: Sales Manager | C8: Sales | D8: karim.adel@beitaksmart.example | E8: Administrator | F8: Administrator | G8: - | H8: User | I8: - | J8: - | K8: Administrator | L8: - | M8: -
A9: Tamer Salah | B9: Warehouse & Logistics Manager | C9: Warehouse & Logistics | D9: tamer.salah@beitaksmart.example | E9: - | F9: - | G9: User | H9: Administrator | I9: User | J9: - | K9: - | L9: - | M9: -
A10: Mohamed Zaki | B10: Production Manager | C10: Production | D10: mohamed.zaki@beitaksmart.example | E10: - | F10: - | G10: - | H10: User | I10: Administrator | J10: - | K10: - | L10: - | M10: -
A11: Dina Samir | B11: HR Manager | C11: Human Resources | D11: dina.samir@beitaksmart.example | E11: - | F11: - | G11: - | H11: - | I11: - | J11: - | K11: - | L11: Administrator | M11: -
A12: Omar Hassan | B12: IT & ERP Administrator | C12: IT & ERP | D12: omar.hassan@beitaksmart.example | E12: Administrator | F12: Administrator | G12: Administrator | H12: Administrator | I12: Administrator | J12: Administrator | K12: Administrator | L12: Administrator | M12: Administration: Settings
A13: Mahmoud Ali | B13: Senior Accountant | C13: Finance & Accounting | D13: mahmoud.ali@beitaksmart.example | E13: - | F13: - | G13: User | H13: - | I13: - | J13: Accountant | K13: - | L13: - | M13: -
A14: Nourhan Ibrahim | B14: Accountant - AP & AR | C14: Finance & Accounting | D14: nourhan.ibrahim@beitaksmart.example | E14: - | F14: - | G14: User | H14: - | I14: - | J14: Accountant | K14: - | L14: - | M14: -
A15: Wael Said | B15: Treasurer / Cashier | C15: Finance & Accounting | D15: wael.said@beitaksmart.example | E15: - | F15: - | G15: - | H15: - | I15: - | J15: Invoicing / Billing | K15: User | L15: - | M15: -
... A34: Aya Hesham | B34: HR Specialist | C34: Human Resources | D34: aya.hesham@beitaksmart.example | E34: - | F34: - | G34: - | H34: - | I34: - | J34: - | K34: - | L34: Officer | M34: -

Sheet Organization Chart
A1: Organization Chart
A2: Departments imported with 05_Departments.xlsx; managers with 08_Department_Managers.xlsx. Counts are formulas.
A4: Department | B4: Parent Department | C4: Manager | D4: Manager Job | E4: Employees | F4: Odoo Users
A5: General Management | B5: - | C5: Hany Mostafa | D5: General Manager | E5: =COUNTIF(Employees!$E$5:$E$40,A5) -> 1 | F5: =COUNTIF('Users per Department'!$C$5:$C$34,A5) -> 1
A6: Finance & Accounting | B6: General Management | C6: Rania Fathy | D6: Finance Manager | E6: =COUNTIF(Employees!$E$5:$E$40,A6) -> 4 | F6: =COUNTIF('Users per Department'!$C$5:$C$34,A6) -> 4
A7: Procurement & Import | B7: General Management | C7: Sherif Nabil | D7: Procurement & Import Manager | E7: =COUNTIF(Employees!$E$5:$E$40,A7) -> 3 | F7: =COUNTIF('Users per Department'!$C$5:$C$34,A7) -> 3
A8: Sales | B8: General Management | C8: Karim Adel | D8: Sales Manager | E8: =COUNTIF(Employees!$E$5:$E$40,A8) -> 7 | F8: =COUNTIF('Users per Department'!$C$5:$C$34,A8) -> 7
A9: Showroom & Retail | B9: Sales | C9: Salma Ashraf | D9: Showroom Supervisor | E9: =COUNTIF(Employees!$E$5:$E$40,A9) -> 3 | F9: =COUNTIF('Users per Department'!$C$5:$C$34,A9) -> 3
A10: Warehouse & Logistics | B10: General Management | C10: Tamer Salah | D10: Warehouse & Logistics Manager | E10: =COUNTIF(Employees!$E$5:$E$40,A10) -> 8 | F10: =COUNTIF('Users per Department'!$C$5:$C$34,A10) -> 6
A11: Production | B11: General Management | C11: Mohamed Zaki | D11: Production Manager | E11: =COUNTIF(Employees!$E$5:$E$40,A11) -> 6 | F11: =COUNTIF('Users per Department'!$C$5:$C$34,A11) -> 2
A12: Quality Control | B12: Production | C12: Nesma Kamel | D12: Quality Control Inspector | E12: =COUNTIF(Employees!$E$5:$E$40,A12) -> 1 | F12: =COUNTIF('Users per Department'!$C$5:$C$34,A12) -> 1
A13: Human Resources | B13: General Management | C13: Dina Samir | D13: HR Manager | E13: =COUNTIF(Employees!$E$5:$E$40,A13) -> 2 | F13: =COUNTIF('Users per Department'!$C$5:$C$34,A13) -> 2
A14: IT & ERP | B14: General Management | C14: Omar Hassan | D14: IT & ERP Administrator | E14: =COUNTIF(Employees!$E$5:$E$40,A14) -> 1 | F14: =COUNTIF('Users per Department'!$C$5:$C$34,A14) -> 1
A15: Total | E15: =SUM(E5:E14) -> 36 | F15: =SUM(F5:F14) -> 30

Sheet Chart of Accounts
A1: Chart of Accounts (CoA)
A2: Beitak Smart accounts + the localization accounts the design uses. The other localization accounts stay as created by Odoo. Numbering: 1 assets, 2 liabilities, 3 equity, 4 costs & expenses, 5 revenue.
A4: Code | B4: Account Name | C4: Type | D4: Group | E4: Reconcile | F4: Currency | G4: Source | H4: Used For
A5: 100001 | B5: Liquidity Transfer | C5: Current Assets | D5: Assets | E5: - | F5: - | G5: Egypt localization (default) | H5: Internal transfers between banks/safes
A6: 101004 | B6: Outstanding Receipts | C6: Current Assets | D6: Assets | E6: - | F6: - | G6: Egypt localization (default) | H6: Bank/cash journals - receipts before reconciliation
A7: 101101 | B7: Main Safe - Cairo Head Office | C7: Bank and Cash | D7: Assets | E7: No | F7: - | G7: Beitak Smart (imported) | H7: Cash journal CSHHO
A8: 101102 | B8: Branch Safe - Alexandria | C8: Bank and Cash | D8: Assets | E8: No | F8: - | G8: Beitak Smart (imported) | H8: Cash journal CSHAL
A9: 101103 | B9: Petty Cash - Sales & Operations | C9: Bank and Cash | D9: Assets | E9: No | F9: - | G9: Beitak Smart (imported) | H9: Cash journal PETTY
A10: 101104 | B10: Showroom Cash Register - Cairo (POS) | C10: Bank and Cash | D10: Assets | E10: No | F10: - | G10: Beitak Smart (imported) | H10: Cash journal POSCS - POS cash payments
A11: 102012 | B11: Accounts Receivable (PoS) | C11: Receivable | D11: Assets | E11: - | F11: - | G11: Egypt localization (default) | H11: POS sessions receivable
A12: 102101 | B12: Banque Misr - EGP Current Account | C12: Bank and Cash | D12: Assets | E12: No | F12: - | G12: Beitak Smart (imported) | H12: Bank journal BMEG
A13: 102102 | B13: National Bank of Egypt - EGP Operating Account | C13: Bank and Cash | D13: Assets | E13: No | F13: - | G13: Beitak Smart (imported) | H13: Bank journal NBEG - also POS card payments
A14: 102103 | B14: CIB - USD Account | C14: Bank and Cash | D14: Assets | E14: No | F14: USD | G14: Beitak Smart (imported) | H14: Bank journal CIBUS (USD) - overseas vendor payments
A15: 102104 | B15: QNB Alahli - EGP Collection Account | C15: Bank and Cash | D15: Assets | E15: No | F15: - | G15: Beitak Smart (imported) | H15: Bank journal QNBEG - customer collections
... A89: 999999 | B89: Undistributed Profits/Losses | C89: Current Year Earnings | D89: Closing | E89: - | F89: - | G89: Egypt localization (default) | H89: Current year result (computed by Odoo)

Sheet Opening Trial Balance
A1: Opening Trial Balance - 2027-01-01
A2: Balances after files 24 (stock) and 27 (journal entry). Inventory lines come from Products_and_Inventory_Data.xlsx > Inventory Valuation. In the import file stock is posted through 190100, which nets to zero.
A4: Code | B4: Account | C4: Type | D4: Debit (EGP) | E4: Credit (EGP)
A5: 101101 | B5: Main Safe - Cairo Head Office | C5: Bank and Cash | D5: 250000 | E5: 0
A6: 101102 | B6: Branch Safe - Alexandria | C6: Bank and Cash | D6: 85000 | E6: 0
A7: 102101 | B7: Banque Misr - EGP Current Account | C7: Bank and Cash | D7: 1850000 | E7: 0
A8: 102102 | B8: National Bank of Egypt - EGP Operating Account | C8: Bank and Cash | D8: 2100000 | E8: 0
A9: 102103 | B9: CIB - USD Account | C9: Bank and Cash | D9: 920000 | E9: 0
A10: 110100 | B10: Trade Receivables - Retailers | C10: Receivable | D10: 2400000 | E10: 0
A11: 110200 | B11: Trade Receivables - Distributors & Key Accounts | C11: Receivable | D11: 1350000 | E11: 0
A12: 110300 | B12: Notes Receivable - Cheques Under Collection | C12: Receivable | D12: 580000 | E12: 0
A13: 110500 | B13: Prepaid Expenses & Rent | C13: Prepayments | D13: 240000 | E13: 0
A14: 110600 | B14: Employee Advances & Custody | C14: Current Assets | D14: 95000 | E14: 0
A15: 120100 | B15: Inventory - Refrigerators & Freezers | C15: Current Assets | D15: 4248100 | E15: 0
A16: 120200 | B16: Inventory - Washing Machines & Dishwashers | C16: Current Assets | D16: 3843200 | E16: 0
... A42: 330100 | B42: Retained Earnings | C42: Equity | D42: 0 | E42: 4201776.5
A43: Total | D43: =SUM(D5:D42) -> 40474776 | E43: =SUM(E5:E42) -> 40474776
C45: Check: Debit - Credit | D45: =D43-E43 -> 0 | E45: =IF(ABS(D45)<0.01,"Balanced","Not balanced") -> Balanced
C46: Equity split
C47: Paid-in capital (310100) | D47: 25000000
C48: Legal reserve (320100) | D48: 1250000
C49: Retained earnings (330100) = assets - liabilities - capital - reserve | D49: 4201776.5
C50: Total equity | D50: =SUM(D47:D49) -> 30451776

Sheet Opening Partner Balances
A1: Opening Balances by Partner (Customers & Vendors)
A2: One journal line per partner so aged receivable/payable and reconciliation work. USD amounts at the assumed opening rate.
A4: Partner | B4: Type | C4: Account | D4: Currency | E4: Amount in Currency | F4: Debit (EGP) | G4: Credit (EGP)
A5: El Nour Electronics Stores | B5: Customer | C5: 110100 | D5: EGP | F5: 520000 | G5: 0
A6: Al Safa Home Appliances | B6: Customer | C6: 110100 | D6: EGP | F6: 310000 | G6: 0
A7: Heliopolis Appliances Center | B7: Customer | C7: 110100 | D7: EGP | F7: 180000 | G7: 0
A8: Alex Home Center | B8: Customer | C8: 110100 | D8: EGP | F8: 420000 | G8: 0
A9: Bahary Electronics | B9: Customer | C9: 110100 | D9: EGP | F9: 160000 | G9: 0
A10: Delta Appliances Mall | B10: Customer | C10: 110100 | D10: EGP | F10: 290000 | G10: 0
A11: Tanta Electric Gallery | B11: Customer | C11: 110100 | D11: EGP | F11: 180000 | G11: 0
A12: Canal Electronics | B12: Customer | C12: 110100 | D12: EGP | F12: 150000 | G12: 0
A13: Assiut Home Appliances | B13: Customer | C13: 110100 | D13: EGP | F13: 140000 | G13: 0
A14: Sohag Electric Center | B14: Customer | C14: 110100 | D14: EGP | F14: 50000 | G14: 0
A15: Upper Egypt Distribution Co. | B15: Customer | C15: 110200 | D15: EGP | F15: 420000 | G15: 0
A16: Nile Delta Trading & Distribution | B16: Customer | C16: 110200 | D16: EGP | F16: 380000 | G16: 0
... A28: Cairo Packaging Co. | B28: Vendor | C28: 211100 | D28: EGP | F28: 0 | G28: 40000
A29: Guangzhou Coolair Appliances Co., Ltd. | B29: Vendor | C29: 211200 | D29: USD | E29: 24000 | F29: 0 | G29: 1200000
A30: Shenzhen Brightway Electronics Co., Ltd. | B30: Vendor | C30: 211200 | D30: USD | E30: 9000 | F30: 0 | G30: 450000
A31: Ningbo Fanmotor Industrial Co., Ltd. | B31: Vendor | C31: 211200 | D31: USD | E31: 6000 | F31: 0 | G31: 300000
A32: Delta Distribution for Home Appliances | B32: Vendor | C32: 212100 | D32: EGP | F32: 0 | G32: 400000
A33: Egyptian Home Industries Agency | B33: Vendor | C33: 212100 | D33: EGP | F33: 0 | G33: 320000
A34: Total | F34: =SUM(F5:F33) -> 4330000 | G34: =SUM(G5:G33) -> 5520000
A36: Reconciliation with trial balance
A37: Account | E37: Per partners (net) | F37: Per trial balance (net) | G37: Difference
A38: 110100 Trade Receivables - Retailers | E38: =SUMIF($C$5:$C$33,"110100",$F$5:$F$33)-SUMIF($C$5:$C$33,"110100",$G$5:$G$33) -> 2400000 | F38: =SUMIF('Opening Trial Balance'!$A$5:$A$42,"110100",'Opening Trial Balance'!$D$5:$D$42)-SUMIF('Opening Trial Balance'!$A$5:$A$42,"110100",'Opening Trial Balance'!$E$5:$E$42) -> 2400000 | G38: =E38-F38 -> 0
A39: 110200 Trade Receivables - Distributors & Key Accounts | E39: =SUMIF($C$5:$C$33,"110200",$F$5:$F$33)-SUMIF($C$5:$C$33,"110200",$G$5:$G$33) -> 1350000 | F39: =SUMIF('Opening Trial Balance'!$A$5:$A$42,"110200",'Opening Trial Balance'!$D$5:$D$42)-SUMIF('Opening Trial Balance'!$A$5:$A$42,"110200",'Opening Trial Balance'!$E$5:$E$42) -> 1350000 | G39: =E39-F39 -> 0
A40: 110300 Notes Receivable - Cheques Under Collection | E40: =SUMIF($C$5:$C$33,"110300",$F$5:$F$33)-SUMIF($C$5:$C$33,"110300",$G$5:$G$33) -> 580000 | F40: =SUMIF('Opening Trial Balance'!$A$5:$A$42,"110300",'Opening Trial Balance'!$D$5:$D$42)-SUMIF('Opening Trial Balance'!$A$5:$A$42,"110300",'Opening Trial Balance'!$E$5:$E$42) -> 580000 | G40: =E40-F40 -> 0
A41: 211100 Trade Payables - Domestic Vendors | E41: =SUMIF($C$5:$C$33,"211100",$F$5:$F$33)-SUMIF($C$5:$C$33,"211100",$G$5:$G$33) -> -2850000 | F41: =SUMIF('Opening Trial Balance'!$A$5:$A$42,"211100",'Opening Trial Balance'!$D$5:$D$42)-SUMIF('Opening Trial Balance'!$A$5:$A$42,"211100",'Opening Trial Balance'!$E$5:$E$42) -> -2850000 | G41: =E41-F41 -> 0
A42: 211200 Trade Payables - Overseas Vendors | E42: =SUMIF($C$5:$C$33,"211200",$F$5:$F$33)-SUMIF($C$5:$C$33,"211200",$G$5:$G$33) -> -1950000 | F42: =SUMIF('Opening Trial Balance'!$A$5:$A$42,"211200",'Opening Trial Balance'!$D$5:$D$42)-SUMIF('Opening Trial Balance'!$A$5:$A$42,"211200",'Opening Trial Balance'!$E$5:$E$42) -> -1950000 | G42: =E42-F42 -> 0
A43: 212100 Notes Payable - Post-dated Cheques Issued | E43: =SUMIF($C$5:$C$33,"212100",$F$5:$F$33)-SUMIF($C$5:$C$33,"212100",$G$5:$G$33) -> -720000 | F43: =SUMIF('Opening Trial Balance'!$A$5:$A$42,"212100",'Opening Trial Balance'!$D$5:$D$42)-SUMIF('Opening Trial Balance'!$A$5:$A$42,"212100",'Opening Trial Balance'!$E$5:$E$42) -> -720000 | G43: =E43-F43 -> 0

Sheet Bank Details
A1: Bank Details
A2: Account numbers and IBANs are placeholders - never put real bank details on GitHub.
A4: Bank | B4: Branch | C4: Account Title | D4: Currency | E4: Account No. | F4: IBAN | G4: Journal | H4: GL Account | I4: Purpose | J4: Opening (EGP) | K4: Opening (USD)
A5: Banque Misr | B5: Nasr City Branch | C5: Beitak Smart - Current | D5: EGP | E5: XXXX-XXXX-0001 | F5: EG00 XXXX XXXX XXXX XXXX XXXX 0001 | G5: BMEG | H5: 102101 Banque Misr - EGP Current Account | I5: Main EGP bank - vendor payments, salaries | J5: 1850000
A6: National Bank of Egypt | B6: Heliopolis Branch | C6: Beitak Smart - Operating | D6: EGP | E6: XXXX-XXXX-0002 | F6: EG00 XXXX XXXX XXXX XXXX XXXX 0002 | G6: NBEG | H6: 102102 National Bank of Egypt - EGP Operating Account | I6: Operating account - POS card settlements | J6: 2100000
A7: Commercial International Bank (CIB) | B7: Smart Village Branch | C7: Beitak Smart - USD | D7: USD | E7: XXXX-XXXX-0003 | F7: EG00 XXXX XXXX XXXX XXXX XXXX 0003 | G7: CIBUS | H7: 102103 CIB - USD Account | I7: USD account - overseas vendor payments (TT) | J7: 920000 | K7: 18400
A8: QNB Alahli | B8: New Cairo Branch | C8: Beitak Smart - Collection | D8: EGP | E8: XXXX-XXXX-0004 | F8: EG00 XXXX XXXX XXXX XXXX XXXX 0004 | G8: QNBEG | H8: 102104 QNB Alahli - EGP Collection Account | I8: Customer collections and cheque deposits | J8: 0
A9: Total | J9: =SUM(J5:J8) -> 4870000

Sheet Cash Safes
A1: Cash Safes and Daily Cash Cycle
A2: 4 cash journals. Maximum balance = amount above which cash is deposited to the bank the same day.
A4: Safe | B4: Location | C4: Custodian | D4: Currency | E4: Journal | F4: GL Account | G4: Max Balance (EGP) | H4: Opening (EGP)
A5: Main Safe - Cairo HO | B5: Head office, Nasr City | C5: Treasurer / Cashier | D5: EGP | E5: CSHHO | F5: 101101 Main Safe - Cairo Head Office | G5: 300000 | H5: 250000
A6: Branch Safe - Alexandria | B6: Alexandria Warehouse | C6: Warehouse Keeper - Alexandria | D6: EGP | E6: CSHAL | F6: 101102 Branch Safe - Alexandria | G6: 100000 | H6: 85000
A7: Petty Cash - Sales & Operations | B7: Head office | C7: Senior Accountant | D7: EGP | E7: PETTY | F7: 101103 Petty Cash - Sales & Operations | G7: 20000 | H7: 0
A8: Showroom Cash Register | B8: Cairo Showroom | C8: Showroom Cashier | D8: EGP | E8: POSCS | F8: 101104 Showroom Cash Register - Cairo (POS) | G8: 50000 | H8: 0
A9: Total | H9: =SUM(H5:H8) -> 335000
A11: Daily cash cycle
A12: Step | B12: Activity | C12: Description
A13: 1 | B13: Opening count | C13: Custodian counts cash and confirms the opening balance in Odoo (cash journal / POS session).
A14: 2 | B14: Receipts | C14: Customer cash receipts registered as payments on the cash journal (or POS cash payments).
A15: 3 | B15: Payments | C15: Small expenses paid from petty cash are recorded with receipts attached; approval by Senior Accountant.
A16: 4 | B16: End-of-day count | C16: Physical count vs Odoo balance; differences posted to 999001 / 999002.
A17: 5 | B17: Bank deposit | C17: Cash above the maximum balance is deposited next morning; recorded as internal transfer (100001 Liquidity Transfer).
A18: 6 | B18: Review | C18: Treasurer reconciles; Finance Manager reviews the cash journal weekly.

Sheet Journals
A1: Chart of Journals
A2: Imported with 02_Journals.xlsx. Sales, purchase, miscellaneous, exchange, inventory valuation and POS journals are created by Odoo.
A4: Journal | B4: Code | C4: Type | D4: Currency | E4: Default Account | F4: Purpose
A5: Banque Misr - EGP | B5: BMEG | C5: Bank | D5: EGP | E5: 102101 Banque Misr - EGP Current Account | F5: Main EGP bank - vendor payments, salaries
A6: National Bank of Egypt - EGP | B6: NBEG | C6: Bank | D6: EGP | E6: 102102 National Bank of Egypt - EGP Operating Account | F6: Operating account - POS card settlements
A7: CIB - USD | B7: CIBUS | C7: Bank | D7: USD | E7: 102103 CIB - USD Account | F7: USD account - overseas vendor payments (TT)
A8: QNB Alahli - EGP | B8: QNBEG | C8: Bank | D8: EGP | E8: 102104 QNB Alahli - EGP Collection Account | F8: Customer collections and cheque deposits
A9: Main Safe - Cairo HO | B9: CSHHO | C9: Cash | D9: EGP | E9: 101101 Main Safe - Cairo Head Office | F9: Head office safe
A10: Branch Safe - Alexandria | B10: CSHAL | C10: Cash | D10: EGP | E10: 101102 Branch Safe - Alexandria | F10: Alexandria branch safe
A11: Petty Cash - Sales & Operations | B11: PETTY | C11: Cash | D11: EGP | E11: 101103 Petty Cash - Sales & Operations | F11: Small operating expenses
A12: Showroom Cash Register | B12: POSCS | C12: Cash | D12: EGP | E12: 101104 Showroom Cash Register - Cairo (POS) | F12: Cash payment method of the Cairo Showroom POS
A13: Opening Balances | B13: OPEN | C13: General | D13: EGP | E13: - | F13: Opening journal entry only
A14: Customer Invoices | B14: INV | C14: Sales | D14: EGP | E14: Income accounts by category | F14: Created by Odoo
A15: Vendor Bills | B15: BILL | C15: Purchase | D15: EGP | E15: Expense / stock interim accounts | F15: Created by Odoo
... A18: Point of Sale | B18: POSS | C18: Sales | D18: EGP | E18: - | F18: Created by the POS app

Sheet Taxes
A1: Tax Chart
A2: VAT 14% and WHT 1% / 2% / 3% as agreed by the team. Rates, categories and thresholds must be reviewed by a tax specialist before go-live.
A4: Tax | B4: Use | C4: Rate | D4: Applies to | E4: Tax Account | F4: Source | G4: Note
A5: VAT 14% (Sales) | B5: Sales | C5: 0.14 | D5: Goods and services sold | E5: 201017 VAT Output | F5: Egypt localization | G5: Default customer tax on all products
A6: VAT 14% (Purchases) | B6: Purchases | C6: 0.14 | D6: Goods and services bought | E6: 104041 VAT Input | F6: Egypt localization | G6: Default vendor tax on all products
A7: VAT Exempt 0% | B7: Sales / Purchases | C7: 0 | D7: Exempt items | E7: - | F7: Egypt localization | G7: Not used by Beitak Smart products
A8: WHT 1% | B8: Purchases | C8: -0.01 | D8: Category per Egyptian WHT schedule - to be confirmed by tax specialist | E8: 201020 WHTax Payable | F8: Egypt localization (verify) | G8: If missing, duplicate a localization WHT tax and set the rate
A9: WHT 2% | B9: Purchases | C9: -0.02 | D9: Category per Egyptian WHT schedule - to be confirmed by tax specialist | E9: 201020 WHTax Payable | F9: Egypt localization (verify) | G9: If missing, duplicate a localization WHT tax and set the rate
A10: WHT 3% | B10: Purchases | C10: -0.03 | D10: Category per Egyptian WHT schedule - to be confirmed by tax specialist | E10: 201020 WHTax Payable | F10: Egypt localization (verify) | G10: If missing, duplicate a localization WHT tax and set the rate

Sheet Analytic Accounting
A1: Analytic Plans and Accounts
A2: Two plans so P&L can be read by business line and by branch (03 and 04 import files).
A4: Plan | B4: Analytic Account | C4: Code | D4: Used For
A5: Business Line | B5: Trading - Home Appliances | C5: TRD | D5: Profitability by business line
A6: Business Line | B6: Manufacturing | C6: MFG | D6: Profitability by business line
A7: Business Line | B7: Services - Installation | C7: SRV | D7: Profitability by business line
A8: Branch | B8: Cairo HO & Main Warehouse | C8: CAI | D8: Profitability by branch / warehouse
A9: Branch | B9: Alexandria Branch | C9: ALX | D9: Profitability by branch / warehouse
A10: Branch | B10: Mansoura Branch | C10: MAN | D10: Profitability by branch / warehouse
A11: Branch | B11: Ismailia Branch | C11: ISM | D11: Profitability by branch / warehouse
A12: Branch | B12: Asyut Branch | C12: ASY | D12: Profitability by branch / warehouse
A13: Branch | B13: Cairo Showroom | C13: SHW | D13: Profitability by branch / warehouse

Sheet Currencies
A1: Currencies and Rates
A2: Rate entered in Accounting > Configuration > Currencies. Project assumption - replace with the official CBE rate if needed.
A4: Currency | B4: Role | C4: Rate Date | D4: EGP per Unit | E4: Used By
A5: EGP | B5: Company currency | C5: - | D5: 1 | E5: All local transactions
A6: USD | B6: Active foreign currency | C6: 2027-01-01 | D6: 50 | E6: CIB USD journal, overseas vendors (Guangzhou, Shenzhen, Ningbo), vendor prices of imported items
