Workbook

Sheet Index
A1: Partners and Operations Cycles
A2: Beitak Smart - Odoo implementation | Entity data (GAWF). Fictional project data; assumptions on the last rows.
A4: Sheet | B4: Content | C4: Instructor requirement
A5: Customers | B5: 18 customers with terms, credit limits, balances | C5: Entity Data 8 - Chart of Customers
A6: Vendors | B6: 14 vendors with currency, terms, incoterms, balances | C6: Entity Data 9 - Chart of Vendors
A7: Payment Terms | B7: Terms used and counts | C7: Partners chart - Payment Terms
A8: Sales Teams | B8: Teams by region | C8: Sales / CRM
A9: CRM Pipeline | B9: Sample opportunities | C9: CRM
A10: Approvals Matrix | B10: Approval rules and Odoo mechanism | C10: Entity Data 14 - Chart of Approvals / Approval Cycle
A11: Cycle - Order to Cash | B11: Sales cycle | C11: Entity Data 15 - Sales Cycle
A12: Cycle - Procure to Pay | B12: Procurement cycle | C12: Entity Data 15 - Procurement Cycle
A13: Cycle - Manufacturing | B13: Fan assembly cycle | C13: Manufacturing
A14: Cycle - Warehouse Operations | B14: Warehouse cycle | C14: Entity Data 15 - Warehouse Operation Cycle
A15: Cycle - POS Daily | B15: Showroom POS cycle | C15: POS
A16: Cycle - Journal to FS | B16: Financial cycle | C16: Entity Data 15 - Financial Cycle
A18: Assumptions
A19: Odoo version | B19: Files target Odoo 18/19 field names (type=Goods + is_storable). On Odoo 17 replace 'type'+'is_storable' with 'detailed_type' = product.
A20: Database | B20: Designed for a NEW clean database with the Egypt fiscal localization. Importing into the old database will clash with existing account codes and products.
A21: Exchange rate | B21: USD/EGP = 50.00 on 2027-01-01. Project assumption, not an official CBE rate.
A22: Landed costs | B22: Cost of imported items = FOB price x 50 x 1.10 (about 10% for freight, duties, clearance and insurance). Assumption.
A23: Sales prices | B23: Sales prices are VAT-exclusive. VAT 14% comes from the Egypt localization default taxes.
A24: Costing | B24: AVCO + automated (perpetual) valuation on all stockable categories. Needed for Landed Costs.
A25: Opening stock | B25: Stock is loaded through Physical Inventory with accounting date 2027-01-01. Its counterpart is account 190100 Opening Stock Clearing, which the opening journal entry closes to zero.
A26: Taxes | B26: VAT 14% and withholding tax 1% / 2% / 3% (team decision). Rates, categories and thresholds must be reviewed by a tax specialist before go-live.
A27: Personal data | B27: All names, emails, phones, tax IDs and bank numbers are fictional placeholders (.example domains).

Sheet Customers
A1: Chart of Customers
A2: Payment method and delivery terms are documented here; terms, pricelist, credit limit and accounts are imported (12_Customers.xlsx).
A4: Code | B4: Customer | C4: Type | D4: City | E4: Sales Team | F4: Price List | G4: Payment Terms | H4: Credit Limit | I4: Receivable Acc. | J4: Payment Method | K4: Delivery Terms | L4: Opening AR | M4: Opening Cheques | N4: Total Exposure | O4: Credit Headroom
A5: CUS-001 | B5: El Nour Electronics Stores | C5: Retailer | D5: Cairo | E5: Cairo & Giza B2B | F5: Wholesale - Retailers | G5: 30 Days | H5: 900000 | I5: 110100 | J5: Bank transfer / post-dated cheques | K5: Delivered to customer store by our fleet (DAP) | L5: 520000 | M5: 200000 | N5: =L5+M5 -> 720000 | O5: =IF(H5>0,H5-N5,"No credit") -> 180000
A6: CUS-002 | B6: Al Safa Home Appliances | C6: Retailer | D6: Giza | E6: Cairo & Giza B2B | F6: Wholesale - Retailers | G6: 30 Days | H6: 400000 | I6: 110100 | J6: Bank transfer / post-dated cheques | K6: Delivered to customer store by our fleet (DAP) | L6: 310000 | M6: 0 | N6: =L6+M6 -> 310000 | O6: =IF(H6>0,H6-N6,"No credit") -> 90000
A7: CUS-003 | B7: Heliopolis Appliances Center | C7: Retailer | D7: Cairo | E7: Cairo & Giza B2B | F7: Wholesale - Retailers | G7: 15 Days | H7: 250000 | I7: 110100 | J7: Bank transfer / post-dated cheques | K7: Delivered to customer store by our fleet (DAP) | L7: 180000 | M7: 0 | N7: =L7+M7 -> 180000 | O7: =IF(H7>0,H7-N7,"No credit") -> 70000
A8: CUS-004 | B8: Maadi Home Center | C8: Retailer | D8: Cairo | E8: Cairo & Giza B2B | F8: Wholesale - Retailers | G8: 15 Days | H8: 200000 | I8: 110100 | J8: Bank transfer / post-dated cheques | K8: Delivered to customer store by our fleet (DAP) | L8: 0 | M8: 0 | N8: =L8+M8 -> 0 | O8: =IF(H8>0,H8-N8,"No credit") -> 200000
A9: CUS-005 | B9: Alex Home Center | C9: Retailer | D9: Alexandria | E9: Alexandria B2B | F9: Wholesale - Retailers | G9: 30 Days | H9: 600000 | I9: 110100 | J9: Bank transfer / post-dated cheques | K9: Delivered to customer store by our fleet (DAP) | L9: 420000 | M9: 0 | N9: =L9+M9 -> 420000 | O9: =IF(H9>0,H9-N9,"No credit") -> 180000
A10: CUS-006 | B10: Bahary Electronics | C10: Retailer | D10: Alexandria | E10: Alexandria B2B | F10: Wholesale - Retailers | G10: 15 Days | H10: 250000 | I10: 110100 | J10: Bank transfer / post-dated cheques | K10: Delivered to customer store by our fleet (DAP) | L10: 160000 | M10: 0 | N10: =L10+M10 -> 160000 | O10: =IF(H10>0,H10-N10,"No credit") -> 90000
A11: CUS-007 | B11: Delta Appliances Mall | C11: Retailer | D11: Mansoura | E11: Delta & Canal B2B | F11: Wholesale - Retailers | G11: 30 Days | H11: 700000 | I11: 110100 | J11: Bank transfer / post-dated cheques | K11: Delivered to customer store by our fleet (DAP) | L11: 290000 | M11: 230000 | N11: =L11+M11 -> 520000 | O11: =IF(H11>0,H11-N11,"No credit") -> 180000
A12: CUS-008 | B12: Tanta Electric Gallery | C12: Retailer | D12: Tanta | E12: Delta & Canal B2B | F12: Wholesale - Retailers | G12: 30 Days | H12: 300000 | I12: 110100 | J12: Bank transfer / post-dated cheques | K12: Delivered to customer store by our fleet (DAP) | L12: 180000 | M12: 0 | N12: =L12+M12 -> 180000 | O12: =IF(H12>0,H12-N12,"No credit") -> 120000
A13: CUS-009 | B13: Canal Electronics | C13: Retailer | D13: Ismailia | E13: Delta & Canal B2B | F13: Wholesale - Retailers | G13: 30 Days | H13: 300000 | I13: 110100 | J13: Bank transfer / post-dated cheques | K13: Delivered to customer store by our fleet (DAP) | L13: 150000 | M13: 0 | N13: =L13+M13 -> 150000 | O13: =IF(H13>0,H13-N13,"No credit") -> 150000
A14: CUS-010 | B14: Port Said Home Store | C14: Retailer | D14: Port Said | E14: Delta & Canal B2B | F14: Wholesale - Retailers | G14: 15 Days | H14: 200000 | I14: 110100 | J14: Bank transfer / post-dated cheques | K14: Delivered to customer store by our fleet (DAP) | L14: 0 | M14: 0 | N14: =L14+M14 -> 0 | O14: =IF(H14>0,H14-N14,"No credit") -> 200000
A15: CUS-011 | B15: Assiut Home Appliances | C15: Retailer | D15: Asyut | E15: Upper Egypt B2B | F15: Wholesale - Retailers | G15: 45 Days | H15: 350000 | I15: 110100 | J15: Bank transfer / post-dated cheques | K15: Delivered to customer store by our fleet (DAP) | L15: 140000 | M15: 0 | N15: =L15+M15 -> 140000 | O15: =IF(H15>0,H15-N15,"No credit") -> 210000
A16: CUS-012 | B16: Sohag Electric Center | C16: Retailer | D16: Sohag | E16: Upper Egypt B2B | F16: Wholesale - Retailers | G16: 30 Days | H16: 200000 | I16: 110100 | J16: Bank transfer / post-dated cheques | K16: Delivered to customer store by our fleet (DAP) | L16: 50000 | M16: 0 | N16: =L16+M16 -> 50000 | O16: =IF(H16>0,H16-N16,"No credit") -> 150000
... A21: CUS-017 | B21: Alexandria Hospitals Network | C21: Corporate | D21: Alexandria | E21: Key Accounts & Corporate | F21: Key Accounts & Corporate | G21: 45 Days | H21: 500000 | I21: 110200 | J21: Bank transfer | K21: Delivered and installed on site | L21: 0 | M21: 0 | N21: =L21+M21 -> 0 | O21: =IF(H21>0,H21-N21,"No credit") -> 500000
A22: CUS-018 | B22: Walk-in Customer (Showroom) | C22: Walk-in | D22: Cairo | E22: Showroom Retail (POS) | F22: Retail - Showroom | G22: Immediate Payment | I22: 110100 | J22: Cash / card (POS) | K22: Showroom pickup or paid home delivery | L22: 0 | M22: 0 | N22: =L22+M22 -> 0 | O22: =IF(H22>0,H22-N22,"No credit") -> No credit
A23: Total | L23: =SUM(L5:L22) -> 3750000 | M23: =SUM(M5:M22) -> 580000 | N23: =SUM(N5:N22) -> 4330000

Sheet Vendors
A1: Chart of Vendors
A2: Overseas vendors invoice in USD (opening at the assumed rate). Landed-cost service vendors have no opening balance.
A4: Code | B4: Vendor | C4: Type | D4: City | E4: Country | F4: Currency | G4: Payment Terms | H4: Payable Acc. | I4: Payment Method | J4: Delivery Terms (Incoterm) | K4: Lead Time | L4: Opening AP (EGP) | M4: Opening AP (USD) | N4: PDC Issued | O4: Total (EGP)
A5: VEN-001 | B5: Delta Distribution for Home Appliances | C5: Local Appliance Supplier | D5: Cairo | E5: Egypt | F5: EGP | G5: 45 Days | H5: 211100 | I5: Bank transfer / post-dated cheques | J5: Delivered to Cairo warehouse (DAP) | K5: 5 | L5: 1200000 | N5: 400000 | O5: =L5+N5 -> 1600000
A6: VEN-002 | B6: Nile Electronics Trading Co. | C6: Local Appliance Supplier | D6: Cairo | E6: Egypt | F6: EGP | G6: 30 Days | H6: 211100 | I6: Bank transfer | J6: Delivered to Cairo warehouse (DAP) | K6: 4 | L6: 650000 | N6: 0 | O6: =L6+N6 -> 650000
A7: VEN-003 | B7: Egyptian Home Industries Agency | C7: Local Appliance Supplier | D7: 10th of Ramadan City | E7: Egypt | F7: EGP | G7: 30 Days | H7: 211100 | I7: Bank transfer / post-dated cheques | J7: Delivered to Cairo warehouse (DAP) | K7: 5 | L7: 700000 | N7: 320000 | O7: =L7+N7 -> 1020000
A8: VEN-004 | B8: Egyptian Steel Sheets Co. | C8: Raw Material Supplier | D8: 10th of Ramadan City | E8: Egypt | F8: EGP | G8: 30 Days | H8: 211100 | I8: Bank transfer | J8: Delivered to Cairo warehouse (DAP) | K8: 7 | L8: 120000 | N8: 0 | O8: =L8+N8 -> 120000
A9: VEN-005 | B9: Delta Plastics & Rubber | C9: Raw Material Supplier | D9: Sadat City | E9: Egypt | F9: EGP | G9: 30 Days | H9: 211100 | I9: Bank transfer | J9: Delivered to Cairo warehouse (DAP) | K9: 7 | L9: 80000 | N9: 0 | O9: =L9+N9 -> 80000
A10: VEN-006 | B10: Misr Copper & Cables | C10: Raw Material Supplier | D10: Shubra El Kheima | E10: Egypt | F10: EGP | G10: 30 Days | H10: 211100 | I10: Bank transfer | J10: Delivered to Cairo warehouse (DAP) | K10: 5 | L10: 60000 | N10: 0 | O10: =L10+N10 -> 60000
A11: VEN-007 | B11: Cairo Packaging Co. | C11: Raw Material Supplier | D11: Obour City | E11: Egypt | F11: EGP | G11: 15 Days | H11: 211100 | I11: Bank transfer | J11: Delivered to Cairo warehouse (DAP) | K11: 3 | L11: 40000 | N11: 0 | O11: =L11+N11 -> 40000
A12: VEN-008 | B12: Guangzhou Coolair Appliances Co., Ltd. | C12: Overseas Supplier | D12: Guangzhou | E12: China | F12: USD | G12: 30% Now, Balance 60 Days | H12: 211200 | I12: Telegraphic transfer (TT) from CIB USD | J12: FOB Guangzhou - sea freight to Alexandria | K12: 60 | L12: 1200000 | M12: 24000 | N12: 0 | O12: =L12+N12 -> 1200000
A13: VEN-009 | B13: Shenzhen Brightway Electronics Co., Ltd. | C13: Overseas Supplier | D13: Shenzhen | E13: China | F13: USD | G13: 45 Days | H13: 211200 | I13: Telegraphic transfer (TT) from CIB USD | J13: CIF Alexandria | K13: 45 | L13: 450000 | M13: 9000 | N13: 0 | O13: =L13+N13 -> 450000
A14: VEN-010 | B14: Ningbo Fanmotor Industrial Co., Ltd. | C14: Overseas Supplier | D14: Ningbo | E14: China | F14: USD | G14: 45 Days | H14: 211200 | I14: Telegraphic transfer (TT) from CIB USD | J14: FOB Ningbo - sea freight to Alexandria | K14: 50 | L14: 300000 | M14: 6000 | N14: 0 | O14: =L14+N14 -> 300000
A15: VEN-011 | B15: Alexandria Freight Forwarding & Logistics | C15: Logistics & Customs | D15: Alexandria | E15: Egypt | F15: EGP | G15: Immediate Payment | H15: 211100 | I15: Bank transfer | J15: Service | L15: 0 | N15: 0 | O15: =L15+N15 -> 0
A16: VEN-012 | B16: Port Said Customs Clearance Office | C16: Logistics & Customs | D16: Port Said | E16: Egypt | F16: EGP | G16: Immediate Payment | H16: 211100 | I16: Bank transfer | J16: Service | L16: 0 | N16: 0 | O16: =L16+N16 -> 0
A17: VEN-013 | B17: Nile Marine Insurance Co. | C17: Logistics & Customs | D17: Cairo | E17: Egypt | F17: EGP | G17: Immediate Payment | H17: 211100 | I17: Bank transfer | J17: Service | L17: 0 | N17: 0 | O17: =L17+N17 -> 0
A18: VEN-014 | B18: Egyptian Customs Authority | C18: Government | D18: Alexandria | E18: Egypt | F18: EGP | G18: Immediate Payment | H18: 211100 | I18: Bank transfer | J18: Government - customs duties | L18: 0 | N18: 0 | O18: =L18+N18 -> 0
A19: Total | L19: =SUM(L5:L18) -> 4800000 | M19: =SUM(M5:M18) -> 39000 | N19: =SUM(N5:N18) -> 720000 | O19: =SUM(O5:O18) -> 5520000

Sheet Payment Terms
A1: Payment Terms
A2: Standard Odoo payment terms - no import needed.
A4: Payment Terms | B4: Typical Use | C4: Customers | D4: Vendors
A5: Immediate Payment | B5: Cash / walk-in, service vendors | C5: =COUNTIF(Customers!$G$5:$G$22,A5) -> 1 | D5: =COUNTIF(Vendors!$G$5:$G$18,A5) -> 4
A6: 15 Days | B6: Small retailers | C6: =COUNTIF(Customers!$G$5:$G$22,A6) -> 4 | D6: =COUNTIF(Vendors!$G$5:$G$18,A6) -> 1
A7: 30 Days | B7: Retailers, local suppliers | C7: =COUNTIF(Customers!$G$5:$G$22,A7) -> 7 | D7: =COUNTIF(Vendors!$G$5:$G$18,A7) -> 5
A8: 45 Days | B8: Distributors, Upper Egypt retailers, some suppliers | C8: =COUNTIF(Customers!$G$5:$G$22,A8) -> 4 | D8: =COUNTIF(Vendors!$G$5:$G$18,A8) -> 3
A9: End of Following Month | B9: Corporate | C9: =COUNTIF(Customers!$G$5:$G$22,A9) -> 1 | D9: =COUNTIF(Vendors!$G$5:$G$18,A9) -> 0
A10: 30% Now, Balance 60 Days | B10: Projects (hotels) and overseas AC supplier | C10: =COUNTIF(Customers!$G$5:$G$22,A10) -> 1 | D10: =COUNTIF(Vendors!$G$5:$G$18,A10) -> 1

Sheet Sales Teams
A1: Sales Teams
A2: Teams imported with 11_Sales_Teams.xlsx; leaders and members are assigned after users are created.
A4: Sales Team | B4: Region | C4: Team Leader | D4: Customers | E4: Opportunities
A5: Cairo & Giza B2B | B5: Cairo & Giza | C5: Amr Fouad | D5: =COUNTIF(Customers!$E$5:$E$22,A5) -> 4 | E5: =COUNTIF('CRM Pipeline'!$C$5:$C$16,A5) -> 2
A6: Alexandria B2B | B6: Alexandria | C6: Islam Reda | D6: =COUNTIF(Customers!$E$5:$E$22,A6) -> 2 | E6: =COUNTIF('CRM Pipeline'!$C$5:$C$16,A6) -> 1
A7: Delta & Canal B2B | B7: Mansoura, Tanta, Ismailia, Port Said | C7: Walid Shawky | D7: =COUNTIF(Customers!$E$5:$E$22,A7) -> 5 | E7: =COUNTIF('CRM Pipeline'!$C$5:$C$16,A7) -> 3
A8: Upper Egypt B2B | B8: Asyut, Sohag, Red Sea | C8: Mina Fawzy | D8: =COUNTIF(Customers!$E$5:$E$22,A8) -> 3 | E8: =COUNTIF('CRM Pipeline'!$C$5:$C$16,A8) -> 2
A9: Key Accounts & Corporate | B9: Corporate & projects (all regions) | C9: Mostafa Gamal | D9: =COUNTIF(Customers!$E$5:$E$22,A9) -> 3 | E9: =COUNTIF('CRM Pipeline'!$C$5:$C$16,A9) -> 4
A10: Showroom Retail (POS) | B10: Cairo Showroom walk-in | C10: Salma Ashraf | D10: =COUNTIF(Customers!$E$5:$E$22,A10) -> 1 | E10: =COUNTIF('CRM Pipeline'!$C$5:$C$16,A10) -> 0

Sheet CRM Pipeline
A1: CRM Pipeline (sample opportunities)
A2: Imported with 26_CRM_Opportunities.xlsx. Stages: New > Qualified > Proposition > Won.
A4: Opportunity | B4: Customer / Prospect | C4: Sales Team | D4: Stage | E4: Expected Revenue | F4: Probability | G4: Weighted Revenue
A5: Red Sea Resort - 120 Split ACs | B5: Red Sea Resorts Hurghada (new prospect) | C5: Key Accounts & Corporate | D5: Qualified | E5: 4200000 | F5: 0.3 | G5: =E5*F5 -> 1260000
A6: Royal Hotels - New Cairo Branch Fit-out (Fridges & TVs) | B6: Royal Hotels Group | C6: Key Accounts & Corporate | D6: Proposition | E6: 2600000 | F6: 0.6 | G6: =E6*F6 -> 1560000
A7: Smart Homes Phase 2 - Kitchen Appliance Packages | B7: Smart Homes Real Estate Development | C7: Key Accounts & Corporate | D7: Qualified | E7: 5500000 | F7: 0.4 | G7: =E7*F7 -> 2200000
A8: Alex Home Center - Summer AC Stock | B8: Alex Home Center | C8: Alexandria B2B | D8: Proposition | E8: 1800000 | F8: 0.7 | G8: =E8*F8 -> 1260000
A9: El Nour Electronics - TV Season Order | B9: El Nour Electronics Stores | C9: Cairo & Giza B2B | D9: Qualified | E9: 950000 | F9: 0.5 | G9: =E9*F9 -> 475000
A10: Delta Appliances Mall - Washing Machines Restock | B10: Delta Appliances Mall | C10: Delta & Canal B2B | D10: Proposition | E10: 780000 | F10: 0.6 | G10: =E10*F10 -> 468000
A11: New Retailer - Hurghada Electronics Hub | B11: Hurghada Electronics Hub (new prospect) | C11: Upper Egypt B2B | D11: New | E11: 600000 | F11: 0.1 | G11: =E11*F11 -> 60000
A12: Beitak Stand Fan - Distributor Deal (500 units) | B12: Upper Egypt Distribution Co. | C12: Upper Egypt B2B | D12: Qualified | E12: 1000000 | F12: 0.5 | G12: =E12*F12 -> 500000
A13: Canal Electronics - Small Appliances Promo | B13: Canal Electronics | C13: Delta & Canal B2B | D13: New | E13: 320000 | F13: 0.3 | G13: =E13*F13 -> 96000
A14: Alexandria Hospitals - Refrigerators for Wards | B14: Alexandria Hospitals Network | C14: Key Accounts & Corporate | D14: Qualified | E14: 1250000 | F14: 0.25 | G14: =E14*F14 -> 312500
A15: Tanta Electric Gallery - Cookers & Ovens | B15: Tanta Electric Gallery | C15: Delta & Canal B2B | D15: New | E15: 410000 | F15: 0.4 | G15: =E15*F15 -> 164000
A16: TV Wall Mounts - Installation Company Contract | B16: Pro Install Services (new prospect) | C16: Cairo & Giza B2B | D16: New | E16: 290000 | F16: 0.2 | G16: =E16*F16 -> 58000
A17: Total | E17: =SUM(E5:E16) -> 19700000 | G17: =SUM(G5:G16) -> 8413500

Sheet Approvals Matrix
A1: Chart of Approvals
A2: Classification follows the instructor's guide: ~70% Standard, 10-15% Workaround, 15-20% Customization.
A4: Process | B4: Trigger | C4: Threshold | D4: Approver | E4: How in Odoo | F4: Classification
A5: Purchase order | B5: PO total | C5: > 250,000 EGP | D5: Procurement & Import Manager | E5: Purchase Order Approval (2-step validation) | F5: Standard
A6: Overseas purchase order (USD) | B6: Any overseas vendor | C6: All amounts | D6: General Manager | E6: GM confirms POs with Purchase Administrator rights; Approvals app if Enterprise | F6: Workaround
A7: Sales order above credit limit | B7: Exposure > credit limit | C7: Per customer | D7: Finance Manager | E7: Sales Credit Limit warning on order and invoice | F7: Standard (warning) / blocking = Customization
A8: Sales discount | B8: Line discount | C8: > 10% | D8: Sales Manager | E8: Approval rule (Studio, Enterprise) or small custom module | F8: Customization
A9: Price list changes | B9: Create / edit price list | C9: All | D9: Sales Manager | E9: Only Sales Administrator can edit price lists | F9: Standard
A10: Vendor payment | B10: Payment amount | C10: > 500,000 EGP | D10: Finance Manager | E10: Treasurer creates draft payment; Finance Manager posts | F10: Workaround
A11: Inventory adjustment | B11: Apply a count | C11: All | D11: Warehouse & Logistics Manager | E11: Apply button limited to Inventory Administrator | F11: Standard
A12: Scrap | B12: Scrap value | C12: > 10,000 EGP | D12: Production Manager | E12: Supervisor scraps; weekly scrap report reviewed by manager | F12: Workaround
A13: Manual journal entries | B13: Post entry | C13: All | D13: Finance Manager | E13: Accountant prepares draft; Finance Manager posts; lock dates | F13: Workaround
A14: POS refund | B14: Refund in POS | C14: All | D14: Showroom Supervisor | E14: Refunds done by POS Administrator; cashier uses employee login | F14: Workaround
A15: Time off | B15: Leave request | C15: All | D15: Direct manager | E15: Time Off approval by manager | F15: Standard

Sheet Cycle - Order to Cash
A1: Sales Cycle - Order to Cash
A2: Each step shows who does it, where in Odoo, the control, and the journal entry it creates.
A4: # | B4: Step | C4: Department | D4: Role | E4: Odoo App | F4: Odoo Document / Action | G4: Control | H4: Accounting Entry
A5: 1 | B5: Capture lead | C5: Sales | D5: Sales Representative | E5: CRM | F5: Lead > Opportunity in pipeline | G5: - | H5: -
A6: 2 | B6: Quotation | C6: Sales | D6: Sales Representative | E6: Sales | F6: Quotation with customer price list | G6: Price list rules | H6: -
A7: 3 | B7: Confirm order | C7: Sales | D7: Sales Representative | E7: Sales | F7: Sales Order | G7: Credit limit warning; discount > 10% needs Sales Manager | H7: -
A8: 4 | B8: Pick and pack | C8: Warehouse & Logistics | D8: Warehouse Keeper | E8: Inventory | F8: CAW: Pick > Pack > Ship; branches: Pick > Ship; scan serials | G8: Serial numbers | H8: -
A9: 5 | B9: Deliver | C9: Warehouse & Logistics | D9: Delivery Driver | E9: Inventory | F9: Delivery Order validated | G9: Customer signature | H9: Dr 120901 Stock Output / Cr 1201xx Inventory
A10: 6 | B10: Invoice | C10: Finance & Accounting | D10: Accountant | E10: Accounting | F10: Customer Invoice (invoice policy: delivered quantities) | G10: - | H10: Dr 110100/110200 AR / Cr 5101xx Sales + 201017 VAT; Dr 4101xx COGS / Cr 120901
A11: 7 | B11: Collect | C11: Finance & Accounting | D11: Treasurer / Cashier | E11: Accounting | F11: Register Payment (bank, cash or post-dated cheque) | G11: - | H11: Dr Bank or 110300 Notes Receivable / Cr AR
A12: 8 | B12: Reconcile | C12: Finance & Accounting | D12: Accountant | E12: Accounting | F12: Bank reconciliation | G12: - | H12: Dr Bank / Cr 101004 Outstanding Receipts
A13: 9 | B13: Follow-up | C13: Finance & Accounting | D13: Accountant | E13: Accounting | F13: Aged Receivable report | G13: Overdue review | H13: -

Sheet Cycle - Procure to Pay
A1: Procurement Cycle - Purchase Request to Payment
A2: Each step shows who does it, where in Odoo, the control, and the journal entry it creates.
A4: # | B4: Step | C4: Department | D4: Role | E4: Odoo App | F4: Odoo Document / Action | G4: Control | H4: Accounting Entry
A5: 1 | B5: Replenishment need | C5: Procurement & Import | D5: Purchasing Specialist | E5: Inventory | F5: Reordering rule or manual RFQ | G5: Min / max rules | H5: -
A6: 2 | B6: Request for quotation | C6: Procurement & Import | D6: Purchasing / Import Specialist | E6: Purchase | F6: RFQ with vendor price list (USD for overseas) | G6: - | H6: -
A7: 3 | B7: Approve order | C7: Procurement & Import | D7: Procurement Manager / GM | E7: Purchase | F7: Purchase Order | G7: Approval above 250,000 EGP | H7: -
A8: 4 | B8: Receive | C8: Warehouse & Logistics | D8: Warehouse Keeper | E8: Inventory | F8: CAW receipt: Input > Quality Control > Stock; serials | G8: Quality check | H8: Dr 1201xx Inventory / Cr 120900 GRNI
A9: 5 | B9: Vendor bill | C9: Finance & Accounting | D9: Accountant | E9: Accounting | F9: Vendor Bill matched to received quantities | G9: 3-way match | H9: Dr 120900 GRNI + 104041 VAT Input / Cr 211100 or 211200 AP
A10: 6 | B10: Landed costs | C10: Procurement & Import | D10: Import Specialist | E10: Inventory | F10: Bills for freight, duties, clearance, insurance > Landed Cost on the receipt | G10: - | H10: Dr 1301xx Clearing / Cr AP; then Dr 1201xx Inventory / Cr 1301xx
A11: 7 | B11: Pay vendor | C11: Finance & Accounting | D11: Treasurer / Cashier | E11: Accounting | F11: Payment (CIB USD TT, EGP bank, or post-dated cheque 212100) | G11: Finance Manager above 500,000 EGP | H11: Dr AP / Cr Bank (FX difference 500011 / 400053)
A12: 8 | B12: Reconcile | C12: Finance & Accounting | D12: Accountant | E12: Accounting | F12: Bank reconciliation | G12: - | H12: Dr 105003 Outstanding Payments / Cr Bank

Sheet Cycle - Manufacturing
A1: Manufacturing Cycle - Fan Assembly
A2: Each step shows who does it, where in Odoo, the control, and the journal entry it creates.
A4: # | B4: Step | C4: Department | D4: Role | E4: Odoo App | F4: Odoo Document / Action | G4: Control | H4: Accounting Entry
A5: 1 | B5: Demand | C5: Production | D5: Production Manager | E5: Manufacturing | F5: MO from reordering rule (fan, fan board) or manual | G5: - | H5: -
A6: 2 | B6: Check components | C6: Production | D6: Production Supervisor | E6: Manufacturing | F6: Component availability; missing raw materials trigger RFQs | G6: - | H6: -
A7: 3 | B7: Sub-assembly first | C7: Production | D7: Electronics Technician | E7: Manufacturing | F7: MO for BTK-MFG-007 fan control board | G7: - | H7: Dr 120850 WIP / Cr 120800 Raw Materials
A8: 4 | B8: Work orders | C8: Production | D8: Assembly Technicians | E8: Manufacturing | F8: Fan MO: Assembly Line 1 > Quality Control & Packing | G8: Time tracking | H8: Dr 120850 WIP / Cr 120800 + 120600 (board)
A9: 5 | B9: Produce | C9: Production | D9: Production Supervisor | E9: Manufacturing | F9: Produce with generated serial numbers | G9: QC inspector check | H9: Dr 120600 Finished Goods / Cr 120850 WIP (incl. labour)
A10: 6 | B10: Scrap | C10: Production | D10: Production Supervisor | E10: Inventory | F10: Scrap order | G10: Manager review above 10,000 EGP | H10: Dr 400036 Write Off Inventory / Cr Inventory
A11: 7 | B11: Move to stock | C11: Warehouse & Logistics | D11: Warehouse Keeper | E11: Inventory | F11: Finished goods to stock / resupply branches | G11: - | H11: -

Sheet Cycle - Warehouse Operations
A1: Warehouse Operation Cycle
A2: Each step shows who does it, where in Odoo, the control, and the journal entry it creates.
A4: # | B4: Step | C4: Department | D4: Role | E4: Odoo App | F4: Odoo Document / Action | G4: Control | H4: Accounting Entry
A5: 1 | B5: Receipt | C5: Warehouse & Logistics | D5: Warehouse Keeper - Cairo | E5: Inventory | F5: 3-step receipt with QC in Cairo; 1-step in branches | G5: QC | H5: Automated stock valuation
A6: 2 | B6: Put-away | C6: Warehouse & Logistics | D6: Warehouse Keeper | E6: Inventory | F6: Store in First Floor (large) / Second Floor (small) / Raw Materials Store | G6: - | H6: -
A7: 3 | B7: Branch resupply | C7: Warehouse & Logistics | D7: Warehouse Manager | E7: Inventory | F7: Inter-warehouse transfer Cairo > branch | G7: - | H7: -
A8: 4 | B8: Delivery | C8: Warehouse & Logistics | D8: Warehouse Keeper | E8: Inventory | F8: Pick > Pack > Ship (Cairo) / Pick > Ship (branches) | G8: Serial scan | H8: COGS via stock output
A9: 5 | B9: Customer return | C9: Warehouse & Logistics | D9: Warehouse Keeper | E9: Inventory | F9: Return transfer to Quality Control | G9: Serial check | H9: Reverses stock valuation
A10: 6 | B10: Cycle count | C10: Warehouse & Logistics | D10: Warehouse Manager | E10: Inventory | F10: Physical Inventory > Apply | G10: Only manager applies | H10: Dr/Cr Inventory vs adjustment account
A11: 7 | B11: Scrap | C11: Warehouse & Logistics | D11: Warehouse Keeper | E11: Inventory | F11: Scrap order | G11: Manager review | H11: Dr 400036 / Cr Inventory
A12: 8 | B12: Replenishment | C12: Warehouse & Logistics | D12: Warehouse Manager | E12: Inventory | F12: Replenishment report (min / max) | G12: - | H12: -

Sheet Cycle - POS Daily
A1: Point of Sale Daily Cycle - Cairo Showroom
A2: Each step shows who does it, where in Odoo, the control, and the journal entry it creates.
A4: # | B4: Step | C4: Department | D4: Role | E4: Odoo App | F4: Odoo Document / Action | G4: Control | H4: Accounting Entry
A5: 1 | B5: Open session | C5: Showroom & Retail | D5: Showroom Cashier | E5: Point of Sale | F5: Open session with opening cash count | G5: - | H5: -
A6: 2 | B6: Sell | C6: Showroom & Retail | D6: Sales Associate / Cashier | E6: Point of Sale | F6: Scan barcode, select serial, Retail price list | G6: - | H6: -
A7: 3 | B7: Take payment | C7: Showroom & Retail | D7: Showroom Cashier | E7: Point of Sale | F7: Cash (POSCS), Card (NBEG), Customer Account | G7: - | H7: -
A8: 4 | B8: Refund | C8: Showroom & Retail | D8: Showroom Supervisor | E8: Point of Sale | F8: Refund order | G8: Supervisor only | H8: -
A9: 5 | B9: Close session | C9: Showroom & Retail | D9: Showroom Cashier | E9: Point of Sale | F9: Closing cash count | G9: Difference to 999001 / 999002 | H9: Dr 101104 / NBEG / 102012 / Cr 5101xx-5104xx + 201017
A10: 6 | B10: Deposit cash | C10: Finance & Accounting | D10: Treasurer / Cashier | E10: Accounting | F10: Internal transfer to bank | G10: Max balance 50,000 EGP | H10: Dr Bank / Cr 101104 via 100001

Sheet Cycle - Journal to FS
A1: Financial Cycle - Journal to Financial Statements
A2: Each step shows who does it, where in Odoo, the control, and the journal entry it creates.
A4: # | B4: Step | C4: Department | D4: Role | E4: Odoo App | F4: Odoo Document / Action | G4: Control | H4: Accounting Entry
A5: 1 | B5: Operational entries | C5: All | D5: System | E5: All apps | F5: Automatic entries from sales, purchase, inventory, POS, manufacturing | G5: - | H5: Automatic
A6: 2 | B6: Manual entries | C6: Finance & Accounting | D6: Accountant | E6: Accounting | F6: Accruals, prepayments, payroll, depreciation (Misc journal) | G6: Finance Manager posts | H6: Per entry
A7: 3 | B7: Bank and cash reconciliation | C7: Finance & Accounting | D7: Accountant / Treasurer | E7: Accounting | F7: Daily / weekly reconciliation | G7: - | H7: Outstanding accounts cleared
A8: 4 | B8: Inventory check | C8: Finance & Accounting | D8: Senior Accountant | E8: Inventory / Accounting | F8: Stock valuation report vs GL 1201xx | G8: Difference = 0 | H8: -
A9: 5 | B9: Landed cost and interim review | C9: Finance & Accounting | D9: Senior Accountant | E9: Accounting | F9: 120900 / 120901 / 1301xx balances explained | G9: - | H9: -
A10: 6 | B10: VAT return | C10: Finance & Accounting | D10: Senior Accountant | E10: Accounting | F10: Egypt tax report | G10: Tax specialist review | H10: -
A11: 7 | B11: Lock period | C11: Finance & Accounting | D11: Finance Manager | E11: Accounting | F11: Lock dates | G11: - | H11: -
A12: 8 | B12: Reports | C12: Finance & Accounting | D12: Finance Manager | E12: Accounting | F12: Trial Balance > P&L > Balance Sheet; analytic by branch and business line | G12: - | H12: -
A13: 9 | B13: Year-end | C13: Finance & Accounting | D13: Finance Manager | E13: Accounting | F13: Current-year result (999999) closed to retained earnings 330100 | G13: - | H13: Dr 999999 / Cr 330100
