Workbook

Sheet Summary
A1: Financial Proposal - Summary
A2: Smart Core - Beitak Smart Odoo ERP Implementation | Khomasi ERP | v1.0 29 Oct 2026. Fictional project figures.
A4: Item | B4: EGP | C4: US$
A5: Implementation services (excl. VAT) | B5: =Services!$E$23 -> 981750
A6: VAT on services | B6: =Services!$E$24 -> 137445
A7: Implementation services (incl. VAT) | B7: =Services!$E$25 -> 1119195
A8: Odoo subscription - year 1 (Custom, offer price) | B8: =Licenses!E5 -> 241200 | C8: =Licenses!D5 -> 4824
A9: Total year-1 investment (excl. VAT) | B9: =B5+B8 -> 1222950
A10: Yearly subscription from year 2 (list price estimate) | B10: =Licenses!E6 -> 295200 | C10: =Licenses!D6 -> 5904
A11: Consultant days | B11: =SUM(Services!C5:C20) -> 142

Sheet Assumptions
A1: Pricing Assumptions
A2: Blue cells are inputs - change them and every sheet recalculates.
A4: Item | B4: Value | C4: Note
A5: PM day rate (EGP) | B5: 7500 | C5: Assumption - Egyptian market
A6: Functional day rate (EGP) | B6: 6000 | C6: Assumption
A7: Technical day rate (EGP) | B7: 6500 | C7: Assumption
A8: Risk contingency | B8: 0.1 | C8: Share of services
A9: VAT on services | B9: 0.14 | C9: To be confirmed by tax specialist
A10: USD / EGP rate | B10: 50 | C10: Project assumption
A11: Users | B11: 30 | C11: Users per Department sheet
A12: Custom plan - offer (US$/user/month) | B12: 13.4 | C12: odoo.com/pricing, 25 Oct 2026
A13: Custom plan - list (US$/user/month) | B13: 16.4 | C13: Struck-through price on pricing page
A14: Standard plan (US$/user/month) | B14: 7.25 | C14: Comparison only - no Studio
A15: Light user (US$/user/month) | B15: 2.9 | C15: Not used - conditions to confirm
A16: Months per year | B16: 12

Sheet Services
A1: Implementation Services
A2: Days per workstream x day rate by role.
A4: Workstream | B4: Role | C4: Days | D4: Rate (EGP) | E4: Amount (EGP)
A5: Project management (planning, steering, reporting, change control) | B5: Project Manager | C5: 22 | D5: =IF(B5="Project Manager",Assumptions!$B$5,IF(B5="Technical",Assumptions!$B$7,Assumptions!$B$6)) -> 7500 | E5: =C5*D5 -> 165000
A6: Discovery & analysis (workshops, BRD, GAWF, RTM) | B6: Functional | C6: 18 | D6: =IF(B6="Project Manager",Assumptions!$B$5,IF(B6="Technical",Assumptions!$B$7,Assumptions!$B$6)) -> 6000 | E6: =C6*D6 -> 108000
A7: Solution design (SSD, TPD) | B7: Functional | C7: 8 | D7: =IF(B7="Project Manager",Assumptions!$B$5,IF(B7="Technical",Assumptions!$B$7,Assumptions!$B$6)) -> 6000 | E7: =C7*D7 -> 48000
A8: Configuration - Accounting | B8: Functional | C8: 8 | D8: =IF(B8="Project Manager",Assumptions!$B$5,IF(B8="Technical",Assumptions!$B$7,Assumptions!$B$6)) -> 6000 | E8: =C8*D8 -> 48000
A9: Configuration - Inventory & landed costs | B9: Functional | C9: 8 | D9: =IF(B9="Project Manager",Assumptions!$B$5,IF(B9="Technical",Assumptions!$B$7,Assumptions!$B$6)) -> 6000 | E9: =C9*D9 -> 48000
A10: Configuration - Manufacturing | B10: Functional | C10: 6 | D10: =IF(B10="Project Manager",Assumptions!$B$5,IF(B10="Technical",Assumptions!$B$7,Assumptions!$B$6)) -> 6000 | E10: =C10*D10 -> 36000
A11: Configuration - Sales & CRM | B11: Functional | C11: 5 | D11: =IF(B11="Project Manager",Assumptions!$B$5,IF(B11="Technical",Assumptions!$B$7,Assumptions!$B$6)) -> 6000 | E11: =C11*D11 -> 30000
A12: Configuration - Point of Sale | B12: Functional | C12: 3 | D12: =IF(B12="Project Manager",Assumptions!$B$5,IF(B12="Technical",Assumptions!$B$7,Assumptions!$B$6)) -> 6000 | E12: =C12*D12 -> 18000
A13: Configuration - Purchase | B13: Functional | C13: 4 | D13: =IF(B13="Project Manager",Assumptions!$B$5,IF(B13="Technical",Assumptions!$B$7,Assumptions!$B$6)) -> 6000 | E13: =C13*D13 -> 24000
A14: Configuration - HR (Employees, Time Off, Attendances) | B14: Functional | C14: 3 | D14: =IF(B14="Project Manager",Assumptions!$B$5,IF(B14="Technical",Assumptions!$B$7,Assumptions!$B$6)) -> 6000 | E14: =C14*D14 -> 18000
A15: Data migration (27 import files, validation, cutover loads) | B15: Functional | C15: 10 | D15: =IF(B15="Project Manager",Assumptions!$B$5,IF(B15="Technical",Assumptions!$B$7,Assumptions!$B$6)) -> 6000 | E15: =C15*D15 -> 60000
A16: Customizations (11 items - RTM register) | B16: Technical | C16: 15 | D16: =IF(B16="Project Manager",Assumptions!$B$5,IF(B16="Technical",Assumptions!$B$7,Assumptions!$B$6)) -> 6500 | E16: =C16*D16 -> 97500
... A20: Hypercare (4 weeks after go-live) | B20: Functional | C20: 8 | D20: =IF(B20="Project Manager",Assumptions!$B$5,IF(B20="Technical",Assumptions!$B$7,Assumptions!$B$6)) -> 6000 | E20: =C20*D20 -> 48000
A21: Subtotal | C21: =SUM(C5:C20) -> 142 | E21: =SUM(E5:E20) -> 892500
A22: Risk contingency | E22: =E21*Assumptions!$B$8 -> 89250
A23: Services total (excl. VAT) | E23: =E21+E22 -> 981750
A24: VAT | E24: =E23*Assumptions!$B$9 -> 137445
A25: Services total (incl. VAT) | E25: =E23+E24 -> 1119195

Sheet Licenses
A1: Odoo Subscription Options
A2: Paid by Beitak Smart to Odoo in USD; converted at the assumed rate.
A4: Option | B4: US$/user/month | C4: Users | D4: Year (US$) | E4: Year (EGP) | F4: Fit
A5: Custom - offer price (recommended) | B5: =Assumptions!$B$12 -> 13.4 | C5: =Assumptions!$B$11 -> 30 | D5: =B5*C5*Assumptions!$B$16 -> 4824 | E5: =D5*Assumptions!$B$10 -> 241200 | F5: Includes Studio
A6: Custom - list price (renewal estimate) | B6: =Assumptions!$B$13 -> 16.4 | C6: =Assumptions!$B$11 -> 30 | D6: =B6*C6*Assumptions!$B$16 -> 5904 | E6: =D6*Assumptions!$B$10 -> 295200 | F6: Budget from year 2
A7: Standard (comparison) | B7: =Assumptions!$B$14 -> 7.25 | C7: =Assumptions!$B$11 -> 30 | D7: =B7*C7*Assumptions!$B$16 -> 2610 | E7: =D7*Assumptions!$B$10 -> 130500 | F7: No Studio - customizations not possible
A8: Light user (not used) | B8: =Assumptions!$B$15 -> 2.9 | C8: =0 -> 0 | D8: =B8*C8*Assumptions!$B$16 -> 0 | E8: =D8*Assumptions!$B$10 -> 0 | F8: Conditions to confirm on odoo.com

Sheet Milestones
A1: Payment Milestones (services)
A2: Percentages are inputs; amounts follow the services total.
A4: Milestone | B4: Planned date | C4: % | D4: Amount excl. VAT (EGP) | E4: Amount incl. VAT (EGP)
A5: M1 Project kick-off | B5: 04 Oct 2026 | C5: 0.2 | D5: =C5*Services!$E$23 -> 196350 | E5: =D5*(1+Assumptions!$B$9) -> 223839
A6: M2 BRD sign-off | B6: 22 Oct 2026 | C6: 0.15 | D6: =C6*Services!$E$23 -> 147262.5 | E6: =D6*(1+Assumptions!$B$9) -> 167879.25
A7: M3 Solution & proposals sign-off | B7: 05 Nov 2026 | C7: 0.15 | D7: =C7*Services!$E$23 -> 147262.5 | E7: =D7*(1+Assumptions!$B$9) -> 167879.25
A8: M4 Configuration & data migration complete | B8: 03 Dec 2026 | C8: 0.2 | D8: =C8*Services!$E$23 -> 196350 | E8: =D8*(1+Assumptions!$B$9) -> 223839
A9: M5 UAT sign-off | B9: 17 Dec 2026 | C9: 0.15 | D9: =C9*Services!$E$23 -> 147262.5 | E9: =D9*(1+Assumptions!$B$9) -> 167879.25
A10: M6 Go-live | B10: 01 Jan 2027 | C10: 0.1 | D10: =C10*Services!$E$23 -> 98175 | E10: =D10*(1+Assumptions!$B$9) -> 111919.5
A11: M7 Hypercare closure | B11: 28 Jan 2027 | C11: 0.05 | D11: =C11*Services!$E$23 -> 49087.5 | E11: =D11*(1+Assumptions!$B$9) -> 55959.75
A12: Total | C12: =SUM(C5:C11) -> 1 | D12: =SUM(D5:D11) -> 981750 | E12: =SUM(E5:E11) -> 1119195
A13: Check: total % = 100% | C13: =IF(ABS(C12-1)<0.0001,"OK","Check") -> OK
