Workbook

Sheet Index
A1: Requirements Traceability Matrix (RTM)
A2: Smart Core - Beitak Smart Odoo ERP Implementation | Version 1.0 | 25 Oct 2026
A4: Sheet | B4: Content | C4: Instructor requirement
A5: RTM | B5: 70 requirements traced end to end | C5: RTM
A6: Fit-Gap Summary | B6: Standard / Workaround / Customization by module | C6: Execute modules 70 / 10-15 / 15-20
A7: Pain Point Coverage | B7: Pain points vs requirements | C7: BRD traceability
A8: Customization Register | B8: Customizations and effort | C8: Input to SSD and FPD
A9: Workaround Register | B9: Workarounds | C9: Input to SSD and training
A11: Assumptions
A12: Odoo version | B12: Files target Odoo 18/19 field names (type=Goods + is_storable). On Odoo 17 replace 'type'+'is_storable' with 'detailed_type' = product.
A13: Database | B13: Designed for a NEW clean database with the Egypt fiscal localization. Importing into the old database will clash with existing account codes and products.
A14: Exchange rate | B14: USD/EGP = 50.00 on 2027-01-01. Project assumption, not an official CBE rate.
A15: Landed costs | B15: Cost of imported items = FOB price x 50 x 1.10 (about 10% for freight, duties, clearance and insurance). Assumption.
A16: Sales prices | B16: Sales prices are VAT-exclusive. VAT 14% comes from the Egypt localization default taxes.
A17: Costing | B17: AVCO + automated (perpetual) valuation on all stockable categories. Needed for Landed Costs.
A18: Opening stock | B18: Stock is loaded through Physical Inventory with accounting date 2027-01-01. Its counterpart is account 190100 Opening Stock Clearing, which the opening journal entry closes to zero.
A19: Taxes | B19: VAT 14% and withholding tax 1% / 2% / 3% (team decision). Rates, categories and thresholds must be reviewed by a tax specialist before go-live.
A20: Personal data | B20: All names, emails, phones, tax IDs and bank numbers are fictional placeholders (.example domains).

Sheet RTM
A1: Requirements Traceability Matrix
A2: Baseline v1.0 25 Oct 2026 - for sign-off at M3. Each BRD requirement is traced to its Odoo solution, SSD section, import file, owner and UAT test case.
A4: Req. ID | B4: Module | C4: Requirement | D4: Priority | E4: Source (pain point) | F4: Fit / Gap | G4: Odoo Solution | H4: SSD Ref. | I4: Import File | J4: Owner | K4: UAT Test Case | L4: Status
A5: BR-CRM-01 | B5: CRM | C5: Capture leads and opportunities from exhibitions, phone, WhatsApp and website in one pipeline (New > Qualified > Proposition > Won / Lost) | D5: Must | E5: PP-08 | F5: Standard | G5: CRM pipeline, stages, lead sources (UTM) | H5: SSD 3.1 | I5: 26 | J5: Noha Gamal | K5: TC-CRM-01 | L5: Planned
A6: BR-CRM-02 | B6: CRM | C6: Assign opportunities to regional sales teams; managers see their team, reps see only their own | D6: Must | E6: PP-08, PP-14 | F6: Standard | G6: Sales teams + access 'Own documents only' | H6: SSD 3.1 | I6: 11 | J6: Noha Gamal | K6: TC-CRM-02 | L6: Planned
A7: BR-CRM-03 | B7: CRM | C7: Schedule follow-up activities and log calls and meetings per opportunity | D7: Should | E7: PP-08 | F7: Standard | G7: Activities and chatter | H7: SSD 3.1 | I7: - | J7: Noha Gamal | K7: TC-CRM-03 | L7: Planned
A8: BR-CRM-04 | B8: CRM | C8: Record lost reasons and analyse win / loss | D8: Should | E8: PP-08 | F8: Standard | G8: Lost reasons + pipeline analysis | H8: SSD 3.1 | I8: - | J8: Noha Gamal | K8: TC-CRM-04 | L8: Planned
A9: BR-CRM-05 | B9: CRM | C9: Monthly revenue target per salesperson with achievement % | D9: Should | E9: PP-09 | F9: Customization | G9: Target field per salesperson + achievement report (Studio) | H9: SSD 3.1 | I9: - | J9: Noha Gamal | K9: TC-CRM-05 | L9: Planned
A10: BR-SAL-01 | B10: Sales | C10: Quotations and sales orders use customer price lists (retail, wholesale, distributors, key accounts) with quantity breaks | D10: Must | E10: PP-02 | F10: Standard | G10: Price lists with advanced rules | H10: SSD 3.2 | I10: 10, 12 | J10: Noha Gamal | K10: TC-SAL-01 | L10: Planned
A11: BR-SAL-02 | B11: Sales | C11: When a list price changes, all price lists update automatically | D11: Must | E11: PP-02 | F11: Standard | G11: Percentage rules based on list price | H11: SSD 3.2 | I11: 10 | J11: Noha Gamal | K11: TC-SAL-02 | L11: Planned
A12: BR-SAL-03 | B12: Sales | C12: Warn the user when a customer's exposure exceeds the credit limit | D12: Must | E12: PP-07 | F12: Standard | G12: Sales Credit Limit (warning on order and invoice) | H12: SSD 3.2 | I12: 12 | J12: Noha Gamal | K12: TC-SAL-03 | L12: Planned
A13: BR-SAL-04 | B13: Sales | C13: Block confirmation of orders above credit limit unless the Finance Manager approves | D13: Should | E13: PP-07 | F13: Customization | G13: Approval check on order confirmation (Studio approval rule / small module) | H13: SSD 3.2 | I13: - | J13: Noha Gamal | K13: TC-SAL-04 | L13: Planned
A14: BR-SAL-05 | B14: Sales | C14: Discounts above 10% require Sales Manager approval | D14: Should | E14: PP-02 | F14: Customization | G14: Approval rule on discount (Studio) | H14: SSD 3.2 | I14: - | J14: Noha Gamal | K14: TC-SAL-05 | L14: Planned
A15: BR-SAL-06 | B15: Sales | C15: Invoice customers on delivered quantities only | D15: Must | E15: PP-10 | F15: Standard | G15: Invoicing policy: delivered quantities | H15: SSD 3.2 | I15: 17 | J15: Noha Gamal | K15: TC-SAL-06 | L15: Planned
... A74: BR-GEN-06 | B74: Cross-functional | C74: Bilingual delivery note and transfer documents with serial numbers and signature box | D74: Should | E74: PP-06 | F74: Customization | G74: Customized delivery report (QWeb) | H74: SSD 3.9 | I74: - | J74: Omar ElSayed | K74: TC-GEN-06 | L74: Planned

Sheet Fit-Gap Summary
A1: Fit / Gap Summary
A2: Instructor target: Standard ~70%, Workaround 10-15%, Customization 15-20%.
A4: Module | B4: Standard | C4: Workaround | D4: Customization | E4: Total
A5: CRM | B5: =COUNTIFS(RTM!$B$5:$B$74,$A5,RTM!$F$5:$F$74,"Standard") | C5: =COUNTIFS(RTM!$B$5:$B$74,$A5,RTM!$F$5:$F$74,"Workaround") | D5: =COUNTIFS(RTM!$B$5:$B$74,$A5,RTM!$F$5:$F$74,"Customization") | E5: =SUM(B5:D5)
A6: Sales | B6: =COUNTIFS(RTM!$B$5:$B$74,$A6,RTM!$F$5:$F$74,"Standard") | C6: =COUNTIFS(RTM!$B$5:$B$74,$A6,RTM!$F$5:$F$74,"Workaround") | D6: =COUNTIFS(RTM!$B$5:$B$74,$A6,RTM!$F$5:$F$74,"Customization") | E6: =SUM(B6:D6)
A7: POS | B7: =COUNTIFS(RTM!$B$5:$B$74,$A7,RTM!$F$5:$F$74,"Standard") | C7: =COUNTIFS(RTM!$B$5:$B$74,$A7,RTM!$F$5:$F$74,"Workaround") | D7: =COUNTIFS(RTM!$B$5:$B$74,$A7,RTM!$F$5:$F$74,"Customization") | E7: =SUM(B7:D7)
A8: Purchase | B8: =COUNTIFS(RTM!$B$5:$B$74,$A8,RTM!$F$5:$F$74,"Standard") | C8: =COUNTIFS(RTM!$B$5:$B$74,$A8,RTM!$F$5:$F$74,"Workaround") | D8: =COUNTIFS(RTM!$B$5:$B$74,$A8,RTM!$F$5:$F$74,"Customization") | E8: =SUM(B8:D8)
A9: Inventory | B9: =COUNTIFS(RTM!$B$5:$B$74,$A9,RTM!$F$5:$F$74,"Standard") | C9: =COUNTIFS(RTM!$B$5:$B$74,$A9,RTM!$F$5:$F$74,"Workaround") | D9: =COUNTIFS(RTM!$B$5:$B$74,$A9,RTM!$F$5:$F$74,"Customization") | E9: =SUM(B9:D9)
A10: Manufacturing | B10: =COUNTIFS(RTM!$B$5:$B$74,$A10,RTM!$F$5:$F$74,"Standard") | C10: =COUNTIFS(RTM!$B$5:$B$74,$A10,RTM!$F$5:$F$74,"Workaround") | D10: =COUNTIFS(RTM!$B$5:$B$74,$A10,RTM!$F$5:$F$74,"Customization") | E10: =SUM(B10:D10)
A11: Accounting | B11: =COUNTIFS(RTM!$B$5:$B$74,$A11,RTM!$F$5:$F$74,"Standard") | C11: =COUNTIFS(RTM!$B$5:$B$74,$A11,RTM!$F$5:$F$74,"Workaround") | D11: =COUNTIFS(RTM!$B$5:$B$74,$A11,RTM!$F$5:$F$74,"Customization") | E11: =SUM(B11:D11)
A12: HR | B12: =COUNTIFS(RTM!$B$5:$B$74,$A12,RTM!$F$5:$F$74,"Standard") | C12: =COUNTIFS(RTM!$B$5:$B$74,$A12,RTM!$F$5:$F$74,"Workaround") | D12: =COUNTIFS(RTM!$B$5:$B$74,$A12,RTM!$F$5:$F$74,"Customization") | E12: =SUM(B12:D12)
A13: Cross-functional | B13: =COUNTIFS(RTM!$B$5:$B$74,$A13,RTM!$F$5:$F$74,"Standard") | C13: =COUNTIFS(RTM!$B$5:$B$74,$A13,RTM!$F$5:$F$74,"Workaround") | D13: =COUNTIFS(RTM!$B$5:$B$74,$A13,RTM!$F$5:$F$74,"Customization") | E13: =SUM(B13:D13)
A14: Total | B14: =SUM(B5:B13) | C14: =SUM(C5:C13) | D14: =SUM(D5:D13) | E14: =SUM(E5:E13)
A16: Share of total | B16: =B14/$E$14 | C16: =C14/$E$14 | D16: =D14/$E$14
A17: Target | B17: about 70% | C17: 10% - 15% | D17: 15% - 20%
A18: Within target? | B18: =IF(AND(B16>=0.65,B16<=0.75),"Yes","Check") | C18: =IF(AND(C16>=0.1,C16<=0.15),"Yes","Check") | D18: =IF(AND(D16>=0.15,D16<=0.2),"Yes","Check")

Sheet Pain Point Coverage
A1: Pain Point Coverage
A2: Every pain point from the BRD is covered by at least one requirement.
A4: Pain Point | B4: Description | C4: Impact | D4: Requirements | E4: Requirement IDs
A5: PP-01 | B5: Landed costs (freight, duties, clearance, insurance) are not added to item cost; margins are overstated | C5: High | D5: =COUNTIF(RTM!$E$5:$E$74,"*"&A5&"*") | E5: BR-SAL-09, BR-PUR-05, BR-PUR-06, BR-PUR-09, BR-INV-08, BR-MRP-03, BR-ACC-12
A6: PP-02 | B6: Price lists are updated manually in Excel after USD changes; customers get outdated or inconsistent prices | C6: High | D6: =COUNTIF(RTM!$E$5:$E$74,"*"&A6&"*") | E6: BR-SAL-01, BR-SAL-02, BR-SAL-05, BR-ACC-03, BR-GEN-03
A7: PP-03 | B7: Frequent stock-outs on fast movers and overstock on slow items; no min/max rules; long import lead times | C7: High | D7: =COUNTIF(RTM!$E$5:$E$74,"*"&A7&"*") | E7: BR-PUR-01, BR-PUR-06, BR-PUR-07, BR-PUR-08, BR-INV-05, BR-MRP-04
A8: PP-04 | B8: No real-time stock visibility across 5 warehouses and the showroom; sales confirm availability by phone | C8: High | D8: =COUNTIF(RTM!$E$5:$E$74,"*"&A8&"*") | E8: BR-INV-01, BR-INV-02, BR-INV-03, BR-INV-04, BR-INV-05, BR-INV-09, BR-GEN-05
A9: PP-05 | B9: Cost of assembled products is unknown; component consumption, labour and scrap are not recorded | C9: High | D9: =COUNTIF(RTM!$E$5:$E$74,"*"&A9&"*") | E9: BR-INV-10, BR-MRP-01, BR-MRP-02, BR-MRP-03, BR-MRP-06, BR-MRP-07, BR-MRP-08
A10: PP-06 | B10: No serial-number traceability for warranty claims and customer returns | C10: Medium | D10: =COUNTIF(RTM!$E$5:$E$74,"*"&A10&"*") | E10: BR-POS-03, BR-INV-06, BR-INV-07, BR-INV-11, BR-MRP-05, BR-GEN-06
A11: PP-07 | B11: Receivables and post-dated cheques tracked in Excel; credit limits not enforced; overdue balances grow | C11: High | D11: =COUNTIF(RTM!$E$5:$E$74,"*"&A11&"*") | E11: BR-SAL-03, BR-SAL-04, BR-ACC-05, BR-ACC-06
A12: PP-08 | B12: Leads from exhibitions, phone and WhatsApp are lost; no pipeline or follow-up | C12: Medium | D12: =COUNTIF(RTM!$E$5:$E$74,"*"&A12&"*") | E12: BR-CRM-01, BR-CRM-02, BR-CRM-03, BR-CRM-04
A13: PP-09 | B13: No profitability by business line (trading, manufacturing, services) or by branch | C13: High | D13: =COUNTIF(RTM!$E$5:$E$74,"*"&A13&"*") | E13: BR-CRM-05, BR-SAL-07, BR-SAL-09, BR-SAL-10, BR-ACC-01, BR-ACC-07, BR-GEN-04
A14: PP-10 | B14: Month-end close takes about 15 working days; data re-keyed between separate files and the legacy accounting package | C14: High | D14: =COUNTIF(RTM!$E$5:$E$74,"*"&A14&"*") | E14: BR-SAL-06, BR-PUR-04, BR-INV-08, BR-ACC-04, BR-ACC-09, BR-ACC-10, BR-ACC-11, BR-GEN-01
A15: PP-11 | B15: Showroom uses a standalone cashier program; stock and accounting are updated manually | C15: Medium | D15: =COUNTIF(RTM!$E$5:$E$74,"*"&A15&"*") | E15: BR-POS-01, BR-POS-02, BR-POS-04
A16: PP-12 | B16: Purchase and payment approvals happen on paper or WhatsApp with no audit trail | C16: Medium | D16: =COUNTIF(RTM!$E$5:$E$74,"*"&A16&"*") | E16: BR-PUR-02, BR-PUR-03, BR-ACC-08, BR-GEN-02
... A18: PP-14 | B18: Shared logins and no segregation of duties in current tools | C18: Medium | D18: =COUNTIF(RTM!$E$5:$E$74,"*"&A18&"*") | E18: BR-CRM-02, BR-POS-05, BR-INV-09, BR-HR-04

Sheet Customization Register
A1: Customization Register
A2: Estimated effort in consultant days (input for the Financial Proposal).
A4: Req. ID | B4: Module | C4: Requirement | D4: Design | E4: Technique | F4: Effort (days)
A5: BR-CRM-05 | B5: CRM | C5: Monthly revenue target per salesperson with achievement % | D5: Target field per salesperson + achievement report (Studio) | E5: Studio | F5: 1
A6: BR-SAL-04 | B6: Sales | C6: Block confirmation of orders above credit limit unless the Finance Manager approves | D6: Approval check on order confirmation (Studio approval rule / small module) | E6: Studio approval rule | F6: 1.5
A7: BR-SAL-05 | B7: Sales | C7: Discounts above 10% require Sales Manager approval | D7: Approval rule on discount (Studio) | E7: Studio approval rule | F7: 1
A8: BR-SAL-08 | B8: Sales | C8: Bilingual (Arabic / English) tax invoice showing tax registration numbers | D8: Customized invoice report (QWeb) | E8: QWeb report | F8: 2
A9: BR-SAL-10 | B9: Sales | C9: Sales commission report per salesperson based on collected invoices | D9: Custom report (collected invoices x commission rate) | E9: Custom report | F9: 2
A10: BR-PUR-06 | B10: Purchase | C10: Track container number, bill of lading and ETA on import POs and receipts | D10: Custom fields on PO and receipt (Studio) | E10: Studio fields | F10: 0.5
A11: BR-PUR-09 | B11: Purchase | C11: Import shipment cost sheet: FOB, freight, duties, clearance and landed cost per unit per container | D11: Custom report on landed costs | E11: Custom report | F11: 2
A12: BR-INV-07 | B12: Inventory | C12: Warranty end date per serial number calculated from the delivery date | D12: Warranty months on product + computed field on serial (Studio) | E12: Studio computed field | F12: 1.5
A13: BR-GEN-03 | B13: Cross-functional | C13: History of product price changes | D13: Field tracking on sales price and cost (Studio) | E13: Studio tracking | F13: 0.5
A14: BR-GEN-05 | B14: Cross-functional | C14: Assign delivery drivers and print a daily trip sheet | D14: Driver field on delivery + trip-sheet report | E14: Studio field + report | F14: 1.5
A15: BR-GEN-06 | B15: Cross-functional | C15: Bilingual delivery note and transfer documents with serial numbers and signature box | D15: Customized delivery report (QWeb) | E15: QWeb report | F15: 1.5
A16: Total | F16: =SUM(F5:F15)

Sheet Workaround Register
A1: Workaround Register
A2: Needs met with standard features used in a specific way - documented for training and the user guides.
A4: Req. ID | B4: Module | C4: Requirement | D4: Workaround
A5: BR-POS-05 | B5: POS | C5: Refunds only by the Showroom Supervisor | D5: Refunds done by POS Administrator; cashiers use employee login
A6: BR-PUR-03 | B6: Purchase | C6: All overseas (USD) POs approved by the General Manager | D6: GM confirms overseas POs with Purchase Administrator rights
A7: BR-INV-10 | B7: Inventory | C7: Scrap recording; scrap above 10,000 EGP reviewed by the Production Manager | D7: Scrap orders + weekly scrap report review
A8: BR-MRP-07 | B8: Manufacturing | C8: Quality check before finished goods move to stock | D8: QC operation in the routing + inspector sign-off (Quality app not in scope)
A9: BR-MRP-08 | B9: Manufacturing | C9: Production performance: planned vs actual time and cost variance | D9: Work order analysis + MO cost comparison
A10: BR-ACC-05 | B10: Accounting | C10: Post-dated cheques received and issued tracked until collection | D10: Notes receivable / payable accounts (110300, 212100) with maturity date in reference
A11: BR-ACC-08 | B11: Accounting | C11: Payments above 500,000 EGP posted only by the Finance Manager | D11: Treasurer drafts payments; Finance Manager posts
A12: BR-GEN-04 | B12: Cross-functional | C12: Management dashboard: sales vs target, stock value, overdue receivables | D12: Standard reports saved to a dashboard / spreadsheet
