Workbook

Sheet Index
A1: User Acceptance Test Document (UATD)
A2: Smart Core - Beitak Smart Odoo ERP Implementation | Khomasi ERP | Version 1.0 | 17 Dec 2026
A4: Sheet | B4: Content | C4: Instructor requirement
A5: Test Plan | B5: Two UAT cycles and sign-off | C5: Testing / UAT phase
A6: Acceptance Criteria | B6: Pass rules and defect severity | C6: UAT governance
A7: Test Cases | B7: 25 scenarios covering all requirements | C7: UATD
A8: Results Summary | B8: Automatic pass / fail summary | C8: UAT reporting
A9: Defects | B9: Defect log | C9: UAT
A10: Sign-off | B10: Signatures of key users and sponsor | C10: M5 sign-off
A12: Assumptions
A13: Odoo version | B13: Files target Odoo 18/19 field names (type=Goods + is_storable). On Odoo 17 replace 'type'+'is_storable' with 'detailed_type' = product.
A14: Database | B14: Designed for a NEW clean database with the Egypt fiscal localization. Importing into the old database will clash with existing account codes and products.
A15: Exchange rate | B15: USD/EGP = 50.00 on 2027-01-01. Project assumption, not an official CBE rate.
A16: Landed costs | B16: Cost of imported items = FOB price x 50 x 1.10 (about 10% for freight, duties, clearance and insurance). Assumption.
A17: Sales prices | B17: Sales prices are VAT-exclusive. VAT 14% comes from the Egypt localization default taxes.
A18: Costing | B18: AVCO + automated (perpetual) valuation on all stockable categories. Needed for Landed Costs.
A19: Opening stock | B19: Stock is loaded through Physical Inventory with accounting date 2027-01-01. Its counterpart is account 190100 Opening Stock Clearing, which the opening journal entry closes to zero.
A20: Taxes | B20: VAT 14% and withholding tax 1% / 2% / 3% (team decision). Rates, categories and thresholds must be reviewed by a tax specialist before go-live.
A21: Personal data | B21: All names, emails, phones, tax IDs and bank numbers are fictional placeholders (.example domains).

Sheet Test Plan
A1: UAT Plan
A2: Two cycles in the test database with migrated data. A case passes only when the expected result is met in full.
A4: Stage | B4: Activity | C4: Start | D4: End | E4: Who
A5: UAT 1 | B5: Cycle 1 - execute all test cases | C5: 06 Dec 2026 | D5: 10 Dec 2026 | E5: Key users with consultant support
A6: Fix | B6: Defect fixing and reconfiguration | C6: 13 Dec 2026 | D6: 14 Dec 2026 | E6: Khomasi ERP consultants
A7: UAT 2 | B7: Cycle 2 - retest failed cases and regression | C7: 15 Dec 2026 | D7: 16 Dec 2026 | E7: Key users
A8: Sign-off | B8: Review results and sign the UATD | C8: 17 Dec 2026 | D8: 17 Dec 2026 | E8: Sponsor and key users

Sheet Acceptance Criteria
A1: Acceptance Criteria and Defect Severity
A2: Agreed before UAT starts.
A4: Item | B4: Definition | C4: Consequence
A5: Pass | B5: All Must requirements pass | C5: Go-live can proceed
A6: Conditional pass | B6: All Must pass; some Should / Could open with an agreed date | C6: Go-live proceeds; open items tracked
A7: Fail | B7: Any Must requirement fails | C7: Go-live postponed until retested
A8: Severity 1 | B8: Blocks a core process (cannot invoice, cannot deliver) | C8: Fixed within 1 working day
A9: Severity 2 | B9: Workaround exists | C9: Fixed before go-live
A10: Severity 3 | B10: Cosmetic or reporting detail | C10: Fixed during hypercare

Sheet Test Cases
A1: User Acceptance Test Cases
A2: 25 end-to-end scenarios covering all 70 requirements. Module = the module that owns the case; a case often crosses modules (see Requirements). Testers fill the last four columns.
A4: Test ID | B4: Module | C4: Scenario | D4: Tester | E4: Steps | F4: Expected Result | G4: Requirements | H4: Priority | I4: Actual Result | J4: Status (Pass / Fail) | K4: Tested by | L4: Date
A5: TC-01 | B5: CRM | C5: Capture a lead and convert it | D5: Sales Representative | E5: 1. CRM > New lead 'Hurghada Electronics Hub', source Exhibition, team Upper Egypt 2. Schedule a call activity 3. Move to Qualified, then convert to opportunity 4. Log a lost reason on another test lead | F5: Lead appears in the rep's pipeline only; activity shows in the chatter; lost reason recorded in the analysis | G5: BR-CRM-01, BR-CRM-02, BR-CRM-03, BR-CRM-04 | H5: Must
A6: TC-02 | B6: Sales | C6: Quotation with wholesale price list | D6: Sales Representative | E6: 1. New quotation for El Nour Electronics 2. Add 12 x LG Smart TV 50 Inch 3. Check unit price against the Wholesale price list (7% off from 10 units) | F6: Price applied automatically from the price list; margin visible to the manager | G6: BR-SAL-01, BR-SAL-02, BR-SAL-09 | H6: Must
A7: TC-03 | B7: Sales | C7: Credit limit warning and approval | D7: Sales Rep + Finance Manager | E7: 1. Create an order for a customer whose exposure exceeds the credit limit 2. Try to confirm 3. Finance Manager approves | F7: Warning shown on the order; confirmation blocked until the Finance Manager approves | G7: BR-SAL-03, BR-SAL-04 | H7: Must
A8: TC-04 | B8: Sales | C8: Discount above 10% | D8: Sales Rep + Sales Manager | E8: 1. Set a 15% line discount 2. Try to confirm the order 3. Sales Manager approves | F8: Confirmation requires Sales Manager approval; approval logged in the chatter | G8: BR-SAL-05 | H8: Should
A9: TC-05 | B9: Sales | C9: Deliver and invoice | D9: Warehouse Keeper + Accountant | E9: 1. Confirm the order 2. Pick, pack and ship with serial scanning 3. Create the invoice 4. Open the journal items | F9: Invoice shows delivered quantities only; entries: AR / revenue + VAT, and COGS / stock output; bilingual layout prints correctly | G9: BR-SAL-06, BR-SAL-08, BR-INV-06, BR-ACC-12 | H9: Must
A10: TC-06 | B10: Accounting | C10: Customer payment and cheque | D10: Treasurer + Accountant | E10: 1. Register a bank payment for one invoice 2. Register a post-dated cheque for another (110300) 3. Reconcile the bank statement 4. Open the Aged Receivable report | F10: Invoices reconciled; cheque sits in notes receivable until collection; aged report matches the customer balance; each bank and cash journal reconciles to its account | G10: BR-ACC-05, BR-ACC-06, BR-ACC-04 | H10: Must
A11: TC-07 | B11: POS | C11: Showroom sale through POS | D11: Showroom Cashier + Supervisor | E11: 1. Open the session with the opening cash count 2. Scan an appliance barcode and select its serial 3. Pay half cash, half card 4. Supervisor refunds a test order 5. Close the session with a cash count | F11: Serial recorded on the order; stock reduced in CAW; cashier cannot refund; closing entry posts to cash, bank and sales; difference to 999001 / 999002 | G11: BR-POS-01, BR-POS-02, BR-POS-03, BR-POS-04, BR-POS-05 | H11: Must
A12: TC-08 | B12: Purchase | C12: Purchase order and approval | D12: Buyer + Procurement Manager | E12: 1. Create a local PO above 250,000 EGP 2. Try to confirm as buyer 3. Procurement Manager approves | F12: PO goes to 'To Approve'; only the manager can confirm | G12: BR-PUR-01, BR-PUR-02 | H12: Must
A13: TC-09 | B13: Purchase | C13: Import shipment with landed costs | D13: Import Specialist + Accountant | E13: 1. PO in USD to Guangzhou Coolair with container and ETA fields 2. GM confirms 3. Receive through Input > QC > Stock 4. Post bills for freight, duties, clearance and insurance 5. Create and validate the landed cost on the receipt 6. Check the product cost and the shipment cost sheet | F13: Product cost increases by the allocated landed costs; clearing accounts 1301xx net to zero; cost sheet shows cost per unit | G13: BR-PUR-03, BR-PUR-05, BR-PUR-06, BR-PUR-09, BR-INV-03 | H13: Must
A14: TC-10 | B14: Purchase | C14: Vendor bill three-way match and USD payment | D14: Accountant + Treasurer | E14: 1. Create the vendor bill from the PO 2. Change a quantity to differ from the receipt 3. Correct it and post 4. Pay from the CIB USD account at a different rate 5. Open the purchase analysis by vendor, product and currency | F14: Bill control flags the mismatch; payment posts the exchange difference to 500011 / 400053; purchase analysis shows both currencies | G14: BR-PUR-04, BR-ACC-03, BR-PUR-07 | H14: Must
A15: TC-11 | B15: Accounting | C15: Withholding tax on a local bill | D15: Accountant | E15: 1. Post a bill for a service vendor with WHT 2. Check the tax lines and the payable amount | F15: WHT reduces the payable and credits 201020; amounts match the agreed rate | G15: BR-ACC-02 | H15: Must
A16: TC-12 | B16: Inventory | C16: Automatic replenishment | D16: Warehouse Manager | E16: 1. Bring a product below its minimum 2. Run Replenishment 3. Check the created RFQ and the created MO for a manufactured item | F16: RFQ created for Buy products and MO for Manufacture products, up to the maximum quantity | G16: BR-INV-02, BR-PUR-08, BR-MRP-04 | H16: Must
... A29: TC-25 | B29: Inventory | C29: Warehouse delivery steps | D29: Warehouse Keeper | E29: 1. Deliver from Cairo (pick, pack, ship) 2. Deliver from Alexandria (pick, ship) | F29: Each warehouse follows its configured steps | G29: BR-INV-04 | H29: Should

Sheet Results Summary
A1: UAT Results Summary
A2: Updates automatically from the Status column of the Test Cases sheet.
A4: Module | B4: Test cases | C4: Passed | D4: Failed | E4: Not tested | F4: Pass %
A5: CRM | B5: =COUNTIF('Test Cases'!$B$5:$B$29,$A5) -> 2 | C5: =COUNTIFS('Test Cases'!$B$5:$B$29,$A5,'Test Cases'!$J$5:$J$29,"Pass") -> 0 | D5: =COUNTIFS('Test Cases'!$B$5:$B$29,$A5,'Test Cases'!$J$5:$J$29,"Fail") -> 0 | E5: =B5-C5-D5 -> 2 | F5: =IF(B5=0,"-",C5/B5) -> 0
A6: Sales | B6: =COUNTIF('Test Cases'!$B$5:$B$29,$A6) -> 5 | C6: =COUNTIFS('Test Cases'!$B$5:$B$29,$A6,'Test Cases'!$J$5:$J$29,"Pass") -> 0 | D6: =COUNTIFS('Test Cases'!$B$5:$B$29,$A6,'Test Cases'!$J$5:$J$29,"Fail") -> 0 | E6: =B6-C6-D6 -> 5 | F6: =IF(B6=0,"-",C6/B6) -> 0
A7: POS | B7: =COUNTIF('Test Cases'!$B$5:$B$29,$A7) -> 1 | C7: =COUNTIFS('Test Cases'!$B$5:$B$29,$A7,'Test Cases'!$J$5:$J$29,"Pass") -> 0 | D7: =COUNTIFS('Test Cases'!$B$5:$B$29,$A7,'Test Cases'!$J$5:$J$29,"Fail") -> 0 | E7: =B7-C7-D7 -> 1 | F7: =IF(B7=0,"-",C7/B7) -> 0
A8: Purchase | B8: =COUNTIF('Test Cases'!$B$5:$B$29,$A8) -> 3 | C8: =COUNTIFS('Test Cases'!$B$5:$B$29,$A8,'Test Cases'!$J$5:$J$29,"Pass") -> 0 | D8: =COUNTIFS('Test Cases'!$B$5:$B$29,$A8,'Test Cases'!$J$5:$J$29,"Fail") -> 0 | E8: =B8-C8-D8 -> 3 | F8: =IF(B8=0,"-",C8/B8) -> 0
A9: Inventory | B9: =COUNTIF('Test Cases'!$B$5:$B$29,$A9) -> 5 | C9: =COUNTIFS('Test Cases'!$B$5:$B$29,$A9,'Test Cases'!$J$5:$J$29,"Pass") -> 0 | D9: =COUNTIFS('Test Cases'!$B$5:$B$29,$A9,'Test Cases'!$J$5:$J$29,"Fail") -> 0 | E9: =B9-C9-D9 -> 5 | F9: =IF(B9=0,"-",C9/B9) -> 0
A10: Manufacturing | B10: =COUNTIF('Test Cases'!$B$5:$B$29,$A10) -> 2 | C10: =COUNTIFS('Test Cases'!$B$5:$B$29,$A10,'Test Cases'!$J$5:$J$29,"Pass") -> 0 | D10: =COUNTIFS('Test Cases'!$B$5:$B$29,$A10,'Test Cases'!$J$5:$J$29,"Fail") -> 0 | E10: =B10-C10-D10 -> 2 | F10: =IF(B10=0,"-",C10/B10) -> 0
A11: Accounting | B11: =COUNTIF('Test Cases'!$B$5:$B$29,$A11) -> 5 | C11: =COUNTIFS('Test Cases'!$B$5:$B$29,$A11,'Test Cases'!$J$5:$J$29,"Pass") -> 0 | D11: =COUNTIFS('Test Cases'!$B$5:$B$29,$A11,'Test Cases'!$J$5:$J$29,"Fail") -> 0 | E11: =B11-C11-D11 -> 5 | F11: =IF(B11=0,"-",C11/B11) -> 0
A12: HR | B12: =COUNTIF('Test Cases'!$B$5:$B$29,$A12) -> 1 | C12: =COUNTIFS('Test Cases'!$B$5:$B$29,$A12,'Test Cases'!$J$5:$J$29,"Pass") -> 0 | D12: =COUNTIFS('Test Cases'!$B$5:$B$29,$A12,'Test Cases'!$J$5:$J$29,"Fail") -> 0 | E12: =B12-C12-D12 -> 1 | F12: =IF(B12=0,"-",C12/B12) -> 0
A13: Cross-functional | B13: =COUNTIF('Test Cases'!$B$5:$B$29,$A13) -> 1 | C13: =COUNTIFS('Test Cases'!$B$5:$B$29,$A13,'Test Cases'!$J$5:$J$29,"Pass") -> 0 | D13: =COUNTIFS('Test Cases'!$B$5:$B$29,$A13,'Test Cases'!$J$5:$J$29,"Fail") -> 0 | E13: =B13-C13-D13 -> 1 | F13: =IF(B13=0,"-",C13/B13) -> 0
A14: Total | B14: =SUM(B5:B13) -> 25 | C14: =SUM(C5:C13) -> 0 | D14: =SUM(D5:D13) -> 0 | E14: =SUM(E5:E13) -> 25 | F14: =IF(B14=0,"-",C14/B14) -> 0
A16: Go-live readiness
A17: All Must test cases passed? | B17: =IF(COUNTIFS('Test Cases'!$H$5:$H$29,"Must",'Test Cases'!$J$5:$J$29,"Pass")=COUNTIF('Test Cases'!$H$5:$H$29,"Must"),"Yes","Not yet") -> Not yet
A18: Open defects (Severity 1 or 2) | B18: =COUNTIFS(Defects!$E$5:$E$200,"<>Closed",Defects!$D$5:$D$200,"<=2") -> 0

Sheet Defects
A1: Defect Log
A2: One row per defect found during UAT. Severity per the Acceptance Criteria sheet.
A4: Defect ID | B4: Test ID | C4: Description | D4: Severity (1-3) | E4: Status | F4: Raised by | G4: Assigned to | H4: Date raised | I4: Date fixed | J4: Retest result
A5: DEF-001 | C5: (example - delete before use) | D5: 3 | E5: Closed

Sheet Sign-off
A1: UAT Sign-off
A2: Signed at milestone M5 on 17 Dec 2026. Signing confirms the tested scope works as designed.
A4: Name | B4: Role | C4: Area tested | D4: Signature | E4: Date
A5: Hany Mostafa | B5: Project Sponsor | C5: Overall acceptance
A6: Rania Fathy | B6: Key User - Accounting | C6: Accounting, opening balances
A7: Karim Adel | B7: Key User - Sales & CRM | C7: Sales, CRM
A8: Salma Ashraf | B8: Key User - Showroom | C8: Point of Sale
A9: Sherif Nabil | B9: Key User - Purchase | C9: Purchase, import, landed costs
A10: Tamer Salah | B10: Key User - Inventory | C10: Warehouses, serials, counts
A11: Mohamed Zaki | B11: Key User - Manufacturing | C11: BOMs, work orders, costing
A12: Dina Samir | B12: Key User - HR | C12: Employees, time off
A13: Noha Gamal | B13: Sales, CRM & POS Consultant - Khomasi ERP | C13: UAT coordination
A14: Ahmed Fahmy | B14: Project Manager - Khomasi ERP | C14: Project
